[{"startTime":"00:00",
 "name":"Phim tài liệu: Hành trình tuổi 20 - Một thời để nhớ (Tập 1)",
 "link":"https://tv360.vn/tv?ch=194&d=2026-03-20&pid=13457927272&00:00+htv9hd",
 "endTime":"00:10",
 "duration":600,
 "datetime":"2026-03-20",
 "dated":"Hôm nay",
 "tvname":"HTV9 HD"},
 {"startTime":"00:10",
 "name":"Giáo dục & hướng nghiệp: Giaó dục giới tính cho trẻ",
 "link":"https://tv360.vn/tv?ch=194&d=2026-03-20&pid=13457927275&00:10+htv9hd",
 "endTime":"00:30",
 "duration":1200,
 "datetime":"2026-03-20",
 "dated":"Hôm nay",
 "tvname":"HTV9 HD"},
 {"startTime":"00:30",
 "name":"Đi để khỏe",
 "link":"https://tv360.vn/tv?ch=194&d=2026-03-20&pid=13457927278&00:30+htv9hd",
 "endTime":"00:50",
 "duration":1200,
 "datetime":"2026-03-20",
 "dated":"Hôm nay",
 "tvname":"HTV9 HD"},
 {"startTime":"00:50",
 "name":"Ống kính thể thao",
 "link":"https://tv360.vn/tv?ch=194&d=2026-03-20&pid=13457927281&00:50+htv9hd",
 "endTime":"01:20",
 "duration":1800,
 "datetime":"2026-03-20",
 "dated":"Hôm nay",
 "tvname":"HTV9 HD"},
 {"startTime":"01:20",
 "name":"Tạp chí thể thao",
 "link":"https://tv360.vn/tv?ch=194&d=2026-03-20&pid=13457927284&01:20+htv9hd",
 "endTime":"01:50",
 "duration":1800,
 "datetime":"2026-03-20",
 "dated":"Hôm nay",
 "tvname":"HTV9 HD"},
 {"startTime":"01:50",
 "name":"Tường thuật One Championship",
 "link":"https://tv360.vn/tv?ch=194&d=2026-03-20&pid=13457927287&01:50+htv9hd",
 "endTime":"02:15",
 "duration":1500,
 "datetime":"2026-03-20",
 "dated":"Hôm nay",
 "tvname":"HTV9 HD"},
 {"startTime":"02:15",
 "name":"Nghệ thuật & cuộc sống: Sách chiếu bóng",
 "link":"https://tv360.vn/tv?ch=194&d=2026-03-20&pid=13457927290&02:15+htv9hd",
 "endTime":"02:30",
 "duration":900,
 "datetime":"2026-03-20",
 "dated":"Hôm nay",
 "tvname":"HTV9 HD"},
 {"startTime":"02:30",
 "name":"Phim tài liệu: Huyền thoại Mẹ Việt Nam anh hùng: Bà Nguyễn Thị Phúc",
 "link":"https://tv360.vn/tv?ch=194&d=2026-03-20&pid=13457927293&02:30+htv9hd",
 "endTime":"03:05",
 "duration":2100,
 "datetime":"2026-03-20",
 "dated":"Hôm nay",
 "tvname":"HTV9 HD"},
 {"startTime":"03:05",
 "name":"Siêu thị cười: Chúng mình hẹn hò",
 "link":"https://tv360.vn/tv?ch=194&d=2026-03-20&pid=13457927296&03:05+htv9hd",
 "endTime":"03:30",
 "duration":1500,
 "datetime":"2026-03-20",
 "dated":"Hôm nay",
 "tvname":"HTV9 HD"},
 {"startTime":"03:30",
 "name":"Chiếu phim: Phim truyện Trung Quốc: Vũ Canh Kỷ",
 "link":"https://tv360.vn/tv?ch=194&d=2026-03-20&pid=13457927299&03:30+htv9hd",
 "endTime":"05:02",
 "duration":5520,
 "datetime":"2026-03-20",
 "dated":"Hôm nay",
 "tvname":"HTV9 HD"},
 {"startTime":"05:02",
 "name":"Thể dục cơ bản",
 "link":"https://tv360.vn/tv?ch=194&d=2026-03-20&pid=13457927302&05:02+htv9hd",
 "endTime":"05:20",
 "duration":1080,
 "datetime":"2026-03-20",
 "dated":"Hôm nay",
 "tvname":"HTV9 HD"},
 {"startTime":"05:20",
 "name":"Thể dục dưỡng sinh",
 "link":"https://tv360.vn/tv?ch=194&d=2026-03-20&pid=13457927305&05:20+htv9hd",
 "endTime":"05:30",
 "duration":600,
 "datetime":"2026-03-20",
 "dated":"Hôm nay",
 "tvname":"HTV9 HD"},
 {"startTime":"05:30",
 "name":"Muôn màu thể thao",
 "link":"https://tv360.vn/tv?ch=194&d=2026-03-20&pid=13457927308&05:30+htv9hd",
 "endTime":"06:00",
 "duration":1800,
 "datetime":"2026-03-20",
 "dated":"Hôm nay",
 "tvname":"HTV9 HD"},
 {"startTime":"06:00",
 "name":"Tin buổi sáng",
 "link":"https://tv360.vn/tv?ch=194&d=2026-03-20&pid=13457927311&06:00+htv9hd",
 "endTime":"06:30",
 "duration":1800,
 "datetime":"2026-03-20",
 "dated":"Hôm nay",
 "tvname":"HTV9 HD"},
 {"startTime":"06:30",
 "name":"Chương trình 60 giây",
 "link":"https://tv360.vn/tv?ch=194&d=2026-03-20&pid=13457927314&06:30+htv9hd",
 "endTime":"07:30",
 "duration":3600,
 "datetime":"2026-03-20",
 "dated":"Hôm nay",
 "tvname":"HTV9 HD"},
 {"startTime":"07:30",
 "name":"Nhìn ra thế giới",
 "link":"https://tv360.vn/tv?ch=194&d=2026-03-20&pid=13457927317&07:30+htv9hd",
 "endTime":"08:00",
 "duration":1800,
 "datetime":"2026-03-20",
 "dated":"Hôm nay",
 "tvname":"HTV9 HD"},
 {"startTime":"08:00",
 "name":"Phim tài liệu: Hành trình tuổi 20 - Một thời để nhớ (Tập 2)",
 "link":"https://tv360.vn/tv?ch=194&d=2026-03-20&pid=13457927320&08:00+htv9hd",
 "endTime":"08:20",
 "duration":1200,
 "datetime":"2026-03-20",
 "dated":"Hôm nay",
 "tvname":"HTV9 HD"},
 {"startTime":"08:20",
 "name":"Thành phố của tôi: Học cách yêu thương",
 "link":"https://tv360.vn/tv?ch=194&d=2026-03-20&pid=13457927323&08:20+htv9hd",
 "endTime":"08:40",
 "duration":1200,
 "datetime":"2026-03-20",
 "dated":"Hôm nay",
 "tvname":"HTV9 HD"},
 {"startTime":"08:40",
 "name":"Phòng cháy chữa cháy",
 "link":"https://tv360.vn/tv?ch=194&d=2026-03-20&pid=13457927326&08:40+htv9hd",
 "endTime":"09:00",
 "duration":1200,
 "datetime":"2026-03-20",
 "dated":"Hôm nay",
 "tvname":"HTV9 HD"},
 {"startTime":"09:00",
 "name":"Tạp chí văn nghệ",
 "link":"https://tv360.vn/tv?ch=194&d=2026-03-20&pid=13457927329&09:00+htv9hd",
 "endTime":"11:30",
 "duration":9000,
 "datetime":"2026-03-20",
 "dated":"Hôm nay",
 "tvname":"HTV9 HD"},
 {"startTime":"11:30",
 "name":"Bản tin trưa",
 "link":"https://tv360.vn/tv?ch=194&d=2026-03-20&pid=13457927332&11:30+htv9hd",
 "endTime":"12:00",
 "duration":1800,
 "datetime":"2026-03-20",
 "dated":"Hôm nay",
 "tvname":"HTV9 HD"},
 {"startTime":"12:00",
 "name":"Chương trình 60 giây",
 "link":"https://tv360.vn/tv?ch=194&d=2026-03-20&pid=13457927335&12:00+htv9hd",
 "endTime":"12:30",
 "duration":1800,
 "datetime":"2026-03-20",
 "dated":"Hôm nay",
 "tvname":"HTV9 HD"},
 {"startTime":"12:30",
 "name":"Cơ hội cho bệnh nhân nghèo",
 "link":"https://tv360.vn/tv?ch=194&d=2026-03-20&pid=13457927338&12:30+htv9hd",
 "endTime":"12:45",
 "duration":900,
 "datetime":"2026-03-20",
 "dated":"Hôm nay",
 "tvname":"HTV9 HD"},
 {"startTime":"12:45",
 "name":"Việt Nam - Đi là ghiền",
 "link":"https://tv360.vn/tv?ch=194&d=2026-03-20&pid=13457927341&12:45+htv9hd",
 "endTime":"13:00",
 "duration":900,
 "datetime":"2026-03-20",
 "dated":"Hôm nay",
 "tvname":"HTV9 HD"},
 {"startTime":"13:00",
 "name":"Chiếu phim: Phim truyện Trung Quốc: Vĩnh dạ tinh hà",
 "link":"https://tv360.vn/tv?ch=194&d=2026-03-20&pid=13457927344&13:00+htv9hd",
 "endTime":"13:30",
 "duration":1800,
 "datetime":"2026-03-20",
 "dated":"Hôm nay",
 "tvname":"HTV9 HD"},
 {"startTime":"13:30",
 "name":"Phụ nữ hiện đại",
 "link":"https://tv360.vn/tv?ch=194&d=2026-03-20&pid=13457927347&13:30+htv9hd",
 "endTime":"13:45",
 "duration":900,
 "datetime":"2026-03-20",
 "dated":"Hôm nay",
 "tvname":"HTV9 HD"},
 {"startTime":"13:45",
 "name":"Hai mùa mưa nắng: Tiểu thư hết thời",
 "link":"https://tv360.vn/tv?ch=194&d=2026-03-20&pid=13457927350&13:45+htv9hd",
 "endTime":"15:00",
 "duration":4500,
 "datetime":"2026-03-20",
 "dated":"Hôm nay",
 "tvname":"HTV9 HD"},
 {"startTime":"15:00",
 "name":"Phim tài liệu: Huyền thoại Mẹ Việt Nam anh hùng: Bà Trần Kim Hoa",
 "link":"https://tv360.vn/tv?ch=194&d=2026-03-20&pid=13457927353&15:00+htv9hd",
 "endTime":"15:20",
 "duration":1200,
 "datetime":"2026-03-20",
 "dated":"Hôm nay",
 "tvname":"HTV9 HD"},
 {"startTime":"15:20",
 "name":"Người trong cuộc",
 "link":"https://tv360.vn/tv?ch=194&d=2026-03-20&pid=13457927356&15:20+htv9hd",
 "endTime":"15:40",
 "duration":1200,
 "datetime":"2026-03-20",
 "dated":"Hôm nay",
 "tvname":"HTV9 HD"},
 {"startTime":"15:40",
 "name":"Muôn màu thể thao",
 "link":"https://tv360.vn/tv?ch=194&d=2026-03-20&pid=13457927359&15:40+htv9hd",
 "endTime":"16:10",
 "duration":1800,
 "datetime":"2026-03-20",
 "dated":"Hôm nay",
 "tvname":"HTV9 HD"},
 {"startTime":"16:10",
 "name":"Nghệ thuật & cuộc sống: Nét cọ nhân sinh",
 "link":"https://tv360.vn/tv?ch=194&d=2026-03-20&pid=13457927362&16:10+htv9hd",
 "endTime":"17:25",
 "duration":4500,
 "datetime":"2026-03-20",
 "dated":"Hôm nay",
 "tvname":"HTV9 HD"},
 {"startTime":"17:25",
 "name":"Trường học siêu sao",
 "link":"https://tv360.vn/tv?ch=194&d=2026-03-20&pid=13457927365&17:25+htv9hd",
 "endTime":"18:10",
 "duration":2700,
 "datetime":"2026-03-20",
 "dated":"Hôm nay",
 "tvname":"HTV9 HD"},
 {"startTime":"18:10",
 "name":"Dấu ấn thương hiệu Việt",
 "link":"https://tv360.vn/tv?ch=194&d=2026-03-20&pid=13457927368&18:10+htv9hd",
 "endTime":"18:30",
 "duration":1200,
 "datetime":"2026-03-20",
 "dated":"Hôm nay",
 "tvname":"HTV9 HD"},
 {"startTime":"18:30",
 "name":"Chương trình 60 giây",
 "link":"https://tv360.vn/tv?ch=194&d=2026-03-20&pid=13457927371&18:30+htv9hd",
 "endTime":"19:00",
 "duration":1800,
 "datetime":"2026-03-20",
 "dated":"Hôm nay",
 "tvname":"HTV9 HD"},
 {"startTime":"19:00",
 "name":"Tiếp sóng VTV",
 "link":"https://tv360.vn/tv?ch=194&d=2026-03-20&pid=13457927374&19:00+htv9hd",
 "endTime":"19:45",
 "duration":2700,
 "datetime":"2026-03-20",
 "dated":"Hôm nay",
 "tvname":"HTV9 HD"},
 {"startTime":"19:45",
 "name":"Thể thao 365",
 "link":"https://tv360.vn/tv?ch=194&d=2026-03-20&pid=13457927377&19:45+htv9hd",
 "endTime":"20:00",
 "duration":900,
 "datetime":"2026-03-20",
 "dated":"Hôm nay",
 "tvname":"HTV9 HD"},
 {"startTime":"20:00",
 "name":"Chương trình thời sự HTV",
 "link":"https://tv360.vn/tv?ch=194&d=2026-03-20&pid=13457927380&20:00+htv9hd",
 "endTime":"20:23",
 "duration":1380,
 "datetime":"2026-03-20",
 "dated":"Hôm nay",
 "tvname":"HTV9 HD"},
 {"startTime":"20:23",
 "name":"Thời tiết du ký",
 "link":"https://tv360.vn/tv?ch=194&d=2026-03-20&pid=13457927383&20:23+htv9hd",
 "endTime":"20:26",
 "duration":180,
 "datetime":"2026-03-20",
 "dated":"Hôm nay",
 "tvname":"HTV9 HD"},
 {"startTime":"20:26",
 "name":"Ăn sạch sống khỏe",
 "link":"https://tv360.vn/tv?ch=194&d=2026-03-20&pid=13457927386&20:26+htv9hd",
 "endTime":"20:33",
 "duration":420,
 "datetime":"2026-03-20",
 "dated":"Hôm nay",
 "tvname":"HTV9 HD"},
 {"startTime":"20:33",
 "name":"Thế giới 24 giờ",
 "link":"https://tv360.vn/tv?ch=194&d=2026-03-20&pid=13457927389&20:33+htv9hd",
 "endTime":"20:45",
 "duration":720,
 "datetime":"2026-03-20",
 "dated":"Hôm nay",
 "tvname":"HTV9 HD"},
 {"startTime":"20:45",
 "name":"Người chung quanh ta",
 "link":"https://tv360.vn/tv?ch=194&d=2026-03-20&pid=13457927392&20:45+htv9hd",
 "endTime":"21:15",
 "duration":1800,
 "datetime":"2026-03-20",
 "dated":"Hôm nay",
 "tvname":"HTV9 HD"},
 {"startTime":"21:15",
 "name":"Góc nhìn HTV",
 "link":"https://tv360.vn/tv?ch=194&d=2026-03-20&pid=13457927395&21:15+htv9hd",
 "endTime":"21:30",
 "duration":900,
 "datetime":"2026-03-20",
 "dated":"Hôm nay",
 "tvname":"HTV9 HD"},
 {"startTime":"21:30",
 "name":"Chuyện bốn mùa: Ai là hoa hậu?",
 "link":"https://tv360.vn/tv?ch=194&d=2026-03-20&pid=13457927398&21:30+htv9hd",
 "endTime":"22:30",
 "duration":3600,
 "datetime":"2026-03-20",
 "dated":"Hôm nay",
 "tvname":"HTV9 HD"},
 {"startTime":"22:30",
 "name":"Chạm 5S: Ca sĩ Xuân Nghi",
 "link":"https://tv360.vn/tv?ch=194&d=2026-03-20&pid=13457927401&22:30+htv9hd",
 "endTime":"23:05",
 "duration":2100,
 "datetime":"2026-03-20",
 "dated":"Hôm nay",
 "tvname":"HTV9 HD"},
 {"startTime":"23:05",
 "name":"Phim tài liệu: Gốm gia dụng Lái Thiêu (Tập 1)",
 "link":"https://tv360.vn/tv?ch=194&d=2026-03-20&pid=13457927404&23:05+htv9hd",
 "endTime":"23:25",
 "duration":1200,
 "datetime":"2026-03-20",
 "dated":"Hôm nay",
 "tvname":"HTV9 HD"},
 {"startTime":"23:25",
 "name":"Nghệ sĩ và sàn diễn: Thực trạng sân khấu cải lương tuồng cổ TP.HCM",
 "link":"https://tv360.vn/tv?ch=194&d=2026-03-20&pid=13457927407&23:25+htv9hd",
 "endTime":"23:55",
 "duration":1800,
 "datetime":"2026-03-20",
 "dated":"Hôm nay",
 "tvname":"HTV9 HD"},
 {"startTime":"23:55",
 "name":"Kịch: Gà trống nuôi con",
 "link":"https://tv360.vn/tv?ch=194&d=2026-03-20&pid=13457927410&23:55+htv9hd",
 "endTime":"23:59",
 "duration":299,
 "datetime":"2026-03-20",
 "dated":"Hôm nay",
 "tvname":"HTV9 HD"}]