[{"startTime":"00:00",
 "name":"Phim Truyện",
 "link":"https://tv360.vn/tv?ch=60&d=2026-03-03&pid=13457233567&00:00+haiphong",
 "endTime":"00:35",
 "duration":2100,
 "datetime":"2026-03-03",
 "dated":"TH3",
 "tvname":"Hải Phòng"},
 {"startTime":"00:35",
 "name":"Tuổi Trẻ Hải Phòng",
 "link":"https://tv360.vn/tv?ch=60&d=2026-03-03&pid=13457233570&00:35+haiphong",
 "endTime":"01:00",
 "duration":1500,
 "datetime":"2026-03-03",
 "dated":"TH3",
 "tvname":"Hải Phòng"},
 {"startTime":"01:00",
 "name":"Phim Truyện",
 "link":"https://tv360.vn/tv?ch=60&d=2026-03-03&pid=13457233573&01:00+haiphong",
 "endTime":"01:45",
 "duration":2700,
 "datetime":"2026-03-03",
 "dated":"TH3",
 "tvname":"Hải Phòng"},
 {"startTime":"01:45",
 "name":"Khoa Học Công Nghệ Và Đời Sống",
 "link":"https://tv360.vn/tv?ch=60&d=2026-03-03&pid=13457233576&01:45+haiphong",
 "endTime":"02:00",
 "duration":900,
 "datetime":"2026-03-03",
 "dated":"TH3",
 "tvname":"Hải Phòng"},
 {"startTime":"02:00",
 "name":"Phim Truyện",
 "link":"https://tv360.vn/tv?ch=60&d=2026-03-03&pid=13457233579&02:00+haiphong",
 "endTime":"02:45",
 "duration":2700,
 "datetime":"2026-03-03",
 "dated":"TH3",
 "tvname":"Hải Phòng"},
 {"startTime":"02:45",
 "name":"Phim Hoạt Hình",
 "link":"https://tv360.vn/tv?ch=60&d=2026-03-03&pid=13457233582&02:45+haiphong",
 "endTime":"03:00",
 "duration":900,
 "datetime":"2026-03-03",
 "dated":"TH3",
 "tvname":"Hải Phòng"},
 {"startTime":"03:00",
 "name":"Phim Truyện",
 "link":"https://tv360.vn/tv?ch=60&d=2026-03-03&pid=13457233585&03:00+haiphong",
 "endTime":"03:45",
 "duration":2700,
 "datetime":"2026-03-03",
 "dated":"TH3",
 "tvname":"Hải Phòng"},
 {"startTime":"03:45",
 "name":"Phim Truyện",
 "link":"https://tv360.vn/tv?ch=60&d=2026-03-03&pid=13457233588&03:45+haiphong",
 "endTime":"04:30",
 "duration":2700,
 "datetime":"2026-03-03",
 "dated":"TH3",
 "tvname":"Hải Phòng"},
 {"startTime":"04:30",
 "name":"Y Tế Sức Khỏe",
 "link":"https://tv360.vn/tv?ch=60&d=2026-03-03&pid=13457233591&04:30+haiphong",
 "endTime":"04:45",
 "duration":900,
 "datetime":"2026-03-03",
 "dated":"TH3",
 "tvname":"Hải Phòng"},
 {"startTime":"04:45",
 "name":"Phim Truyện",
 "link":"https://tv360.vn/tv?ch=60&d=2026-03-03&pid=13457233594&04:45+haiphong",
 "endTime":"05:30",
 "duration":2700,
 "datetime":"2026-03-03",
 "dated":"TH3",
 "tvname":"Hải Phòng"},
 {"startTime":"05:30",
 "name":"Thể Dục Buổi Sáng",
 "link":"https://tv360.vn/tv?ch=60&d=2026-03-03&pid=13457233597&05:30+haiphong",
 "endTime":"05:45",
 "duration":900,
 "datetime":"2026-03-03",
 "dated":"TH3",
 "tvname":"Hải Phòng"},
 {"startTime":"05:45",
 "name":"Vì Cộng Đồng",
 "link":"https://tv360.vn/tv?ch=60&d=2026-03-03&pid=13457233600&05:45+haiphong",
 "endTime":"06:14",
 "duration":1740,
 "datetime":"2026-03-03",
 "dated":"TH3",
 "tvname":"Hải Phòng"},
 {"startTime":"06:14",
 "name":"Bản Tin Thời Sự Sáng",
 "link":"https://tv360.vn/tv?ch=60&d=2026-03-03&pid=13457233603&06:14+haiphong",
 "endTime":"06:30",
 "duration":960,
 "datetime":"2026-03-03",
 "dated":"TH3",
 "tvname":"Hải Phòng"},
 {"startTime":"06:30",
 "name":"Phim Truyện Việt Nam Lụa (Tập 8)",
 "link":"https://tv360.vn/tv?ch=60&d=2026-03-03&pid=13457233606&06:30+haiphong",
 "endTime":"07:17",
 "duration":2820,
 "datetime":"2026-03-03",
 "dated":"TH3",
 "tvname":"Hải Phòng"},
 {"startTime":"07:17",
 "name":"Phim Hoạt Hình",
 "link":"https://tv360.vn/tv?ch=60&d=2026-03-03&pid=13457233609&07:17+haiphong",
 "endTime":"07:30",
 "duration":780,
 "datetime":"2026-03-03",
 "dated":"TH3",
 "tvname":"Hải Phòng"},
 {"startTime":"07:30",
 "name":"Sống Khỏe Cùng Bạn",
 "link":"https://tv360.vn/tv?ch=60&d=2026-03-03&pid=13457233612&07:30+haiphong",
 "endTime":"08:30",
 "duration":3600,
 "datetime":"2026-03-03",
 "dated":"TH3",
 "tvname":"Hải Phòng"},
 {"startTime":"08:30",
 "name":"Lăng Kính Tuổi Hoa",
 "link":"https://tv360.vn/tv?ch=60&d=2026-03-03&pid=13457233615&08:30+haiphong",
 "endTime":"08:51",
 "duration":1260,
 "datetime":"2026-03-03",
 "dated":"TH3",
 "tvname":"Hải Phòng"},
 {"startTime":"08:51",
 "name":"Hộp Thư Truyền Hình",
 "link":"https://tv360.vn/tv?ch=60&d=2026-03-03&pid=13457233618&08:51+haiphong",
 "endTime":"09:01",
 "duration":600,
 "datetime":"2026-03-03",
 "dated":"TH3",
 "tvname":"Hải Phòng"},
 {"startTime":"09:01",
 "name":"Xây Dựng Đảng",
 "link":"https://tv360.vn/tv?ch=60&d=2026-03-03&pid=13457233621&09:01+haiphong",
 "endTime":"09:22",
 "duration":1260,
 "datetime":"2026-03-03",
 "dated":"TH3",
 "tvname":"Hải Phòng"},
 {"startTime":"09:22",
 "name":"An Toàn Giao Thông",
 "link":"https://tv360.vn/tv?ch=60&d=2026-03-03&pid=13457233624&09:22+haiphong",
 "endTime":"09:45",
 "duration":1380,
 "datetime":"2026-03-03",
 "dated":"TH3",
 "tvname":"Hải Phòng"},
 {"startTime":"09:45",
 "name":"Phim Hoạt Hình",
 "link":"https://tv360.vn/tv?ch=60&d=2026-03-03&pid=13457233627&09:45+haiphong",
 "endTime":"10:01",
 "duration":960,
 "datetime":"2026-03-03",
 "dated":"TH3",
 "tvname":"Hải Phòng"},
 {"startTime":"10:01",
 "name":"Phim Truyện",
 "link":"https://tv360.vn/tv?ch=60&d=2026-03-03&pid=13457233630&10:01+haiphong",
 "endTime":"10:45",
 "duration":2640,
 "datetime":"2026-03-03",
 "dated":"TH3",
 "tvname":"Hải Phòng"},
 {"startTime":"10:45",
 "name":"Tuổi Trẻ Hải Phòng",
 "link":"https://tv360.vn/tv?ch=60&d=2026-03-03&pid=13457233633&10:45+haiphong",
 "endTime":"11:11",
 "duration":1560,
 "datetime":"2026-03-03",
 "dated":"TH3",
 "tvname":"Hải Phòng"},
 {"startTime":"11:11",
 "name":"Khoa Học Công Nghệ Và Đời Sống",
 "link":"https://tv360.vn/tv?ch=60&d=2026-03-03&pid=13457233636&11:11+haiphong",
 "endTime":"11:30",
 "duration":1140,
 "datetime":"2026-03-03",
 "dated":"TH3",
 "tvname":"Hải Phòng"},
 {"startTime":"11:30",
 "name":"Bản Tin Thời Sự Trưa",
 "link":"https://tv360.vn/tv?ch=60&d=2026-03-03&pid=13457233639&11:30+haiphong",
 "endTime":"11:59",
 "duration":1740,
 "datetime":"2026-03-03",
 "dated":"TH3",
 "tvname":"Hải Phòng"},
 {"startTime":"11:59",
 "name":"Phim Truyện",
 "link":"https://tv360.vn/tv?ch=60&d=2026-03-03&pid=13457233642&11:59+haiphong",
 "endTime":"12:44",
 "duration":2700,
 "datetime":"2026-03-03",
 "dated":"TH3",
 "tvname":"Hải Phòng"},
 {"startTime":"12:00",
 "name":"Phim Truyện Trung Quốc: Thanh Xuân Có Bạn (Tập 22)",
 "link":"https://tv360.vn/tv?ch=60&d=2026-03-03&pid=13457256790&12:00+haiphong",
 "endTime":"12:45",
 "duration":2700,
 "datetime":"2026-03-03",
 "dated":"TH3",
 "tvname":"Hải Phòng"},
 {"startTime":"12:44",
 "name":"Phim Hoạt Hình",
 "link":"https://tv360.vn/tv?ch=60&d=2026-03-03&pid=13457233645&12:44+haiphong",
 "endTime":"12:58",
 "duration":840,
 "datetime":"2026-03-03",
 "dated":"TH3",
 "tvname":"Hải Phòng"},
 {"startTime":"12:45",
 "name":"Khoa Học Công Nghệ Và Đời Sống: Tạo \"Đòn Bẩy\" Thúc Đẩy Khoa Học Công Nghệ Và Đổi Mới Sáng Tạo",
 "link":"https://tv360.vn/tv?ch=60&d=2026-03-03&pid=13457256793&12:45+haiphong",
 "endTime":"13:00",
 "duration":900,
 "datetime":"2026-03-03",
 "dated":"TH3",
 "tvname":"Hải Phòng"},
 {"startTime":"13:00",
 "name":"Phim Truyện Trung Quốc: Cẩm Y Chi Hạ (Tập 28)",
 "link":"https://tv360.vn/tv?ch=60&d=2026-03-03&pid=13457256796&13:00+haiphong",
 "endTime":"13:45",
 "duration":2700,
 "datetime":"2026-03-03",
 "dated":"TH3",
 "tvname":"Hải Phòng"},
 {"startTime":"13:45",
 "name":"Chuyển Đổi Số Và Cải Cách Hành Chính: Cải Cách Hành Chính Tại Sở Xây Dựng: Minh Bạch- Hiệu Quả",
 "link":"https://tv360.vn/tv?ch=60&d=2026-03-03&pid=13457256799&13:45+haiphong",
 "endTime":"14:00",
 "duration":900,
 "datetime":"2026-03-03",
 "dated":"TH3",
 "tvname":"Hải Phòng"},
 {"startTime":"14:00",
 "name":"Góc Nhìn Thể Thao: Kiện Tướng Của Bóng Bàn Việt Nam",
 "link":"https://tv360.vn/tv?ch=60&d=2026-03-03&pid=13457256802&14:00+haiphong",
 "endTime":"14:15",
 "duration":900,
 "datetime":"2026-03-03",
 "dated":"TH3",
 "tvname":"Hải Phòng"},
 {"startTime":"14:15",
 "name":"Chân Dung Cuộc Sống: Người Thổi Hồn Ngựa Vào Gốm",
 "link":"https://tv360.vn/tv?ch=60&d=2026-03-03&pid=13457256805&14:15+haiphong",
 "endTime":"14:20",
 "duration":300,
 "datetime":"2026-03-03",
 "dated":"TH3",
 "tvname":"Hải Phòng"},
 {"startTime":"14:20",
 "name":"Hải Phòng Văn Hóa Và Sự Kiện: Hải Phòng Viết Tiếp Thiên Hùng Ca",
 "link":"https://tv360.vn/tv?ch=60&d=2026-03-03&pid=13457256808&14:20+haiphong",
 "endTime":"15:00",
 "duration":2400,
 "datetime":"2026-03-03",
 "dated":"TH3",
 "tvname":"Hải Phòng"},
 {"startTime":"15:00",
 "name":"Phim Truyện Việt Nam: Bánh Mì Ông Màu - Phần 2 (Tập 16)",
 "link":"https://tv360.vn/tv?ch=60&d=2026-03-03&pid=13457256811&15:00+haiphong",
 "endTime":"15:45",
 "duration":2700,
 "datetime":"2026-03-03",
 "dated":"TH3",
 "tvname":"Hải Phòng"},
 {"startTime":"15:45",
 "name":"Đại Biểu Nhân Dân Với Cử Tri: Hướng Về Ngày Bầu Cử: Phát Huy Quyền Làm Chủ Của Nhân Dân",
 "link":"https://tv360.vn/tv?ch=60&d=2026-03-03&pid=13457256814&15:45+haiphong",
 "endTime":"16:05",
 "duration":1200,
 "datetime":"2026-03-03",
 "dated":"TH3",
 "tvname":"Hải Phòng"},
 {"startTime":"16:05",
 "name":"Góc Nhìn Nội Chính: Chung Tay Bảo Đảm Quyền Làm Chủ Của Nhân Dân",
 "link":"https://tv360.vn/tv?ch=60&d=2026-03-03&pid=13457256817&16:05+haiphong",
 "endTime":"16:30",
 "duration":1500,
 "datetime":"2026-03-03",
 "dated":"TH3",
 "tvname":"Hải Phòng"},
 {"startTime":"16:30",
 "name":"Nhịp Sống 24h",
 "link":"https://tv360.vn/tv?ch=60&d=2026-03-03&pid=13457256820&16:30+haiphong",
 "endTime":"17:00",
 "duration":1800,
 "datetime":"2026-03-03",
 "dated":"TH3",
 "tvname":"Hải Phòng"},
 {"startTime":"17:00",
 "name":"Phim Truyện Trung Quốc: Lưu Công Kỳ Án (Tập 33)",
 "link":"https://tv360.vn/tv?ch=60&d=2026-03-03&pid=13457256823&17:00+haiphong",
 "endTime":"17:50",
 "duration":3000,
 "datetime":"2026-03-03",
 "dated":"TH3",
 "tvname":"Hải Phòng"},
 {"startTime":"17:50",
 "name":"Bản Tin Thể Thao",
 "link":"https://tv360.vn/tv?ch=60&d=2026-03-03&pid=13457256826&17:50+haiphong",
 "endTime":"18:00",
 "duration":600,
 "datetime":"2026-03-03",
 "dated":"TH3",
 "tvname":"Hải Phòng"},
 {"startTime":"18:00",
 "name":"Lăng Kính Tuổi Hoa: Đỗ Tuấn Kiệt",
 "link":"https://tv360.vn/tv?ch=60&d=2026-03-03&pid=13457256829&18:00+haiphong",
 "endTime":"18:30",
 "duration":1800,
 "datetime":"2026-03-03",
 "dated":"TH3",
 "tvname":"Hải Phòng"},
 {"startTime":"18:30",
 "name":"Bản Tin Quốc Tế",
 "link":"https://tv360.vn/tv?ch=60&d=2026-03-03&pid=13457256832&18:30+haiphong",
 "endTime":"18:40",
 "duration":600,
 "datetime":"2026-03-03",
 "dated":"TH3",
 "tvname":"Hải Phòng"},
 {"startTime":"18:40",
 "name":"Chương Trình 10 Phút Vàng",
 "link":"https://tv360.vn/tv?ch=60&d=2026-03-03&pid=13457256835&18:40+haiphong",
 "endTime":"19:00",
 "duration":1200,
 "datetime":"2026-03-03",
 "dated":"TH3",
 "tvname":"Hải Phòng"},
 {"startTime":"19:00",
 "name":"Chuyển Tiếp Thời Sự Đài Truyền Hình Việt Nam",
 "link":"https://tv360.vn/tv?ch=60&d=2026-03-03&pid=13457256838&19:00+haiphong",
 "endTime":"19:45",
 "duration":2700,
 "datetime":"2026-03-03",
 "dated":"TH3",
 "tvname":"Hải Phòng"},
 {"startTime":"19:45",
 "name":"Bản Tin Thời Sự Tối",
 "link":"https://tv360.vn/tv?ch=60&d=2026-03-03&pid=13457256841&19:45+haiphong",
 "endTime":"20:30",
 "duration":2700,
 "datetime":"2026-03-03",
 "dated":"TH3",
 "tvname":"Hải Phòng"},
 {"startTime":"20:30",
 "name":"Phim Truyện Trung Quốc: Cảm Ơn Bác Sĩ (Tập 39)",
 "link":"https://tv360.vn/tv?ch=60&d=2026-03-03&pid=13457256844&20:30+haiphong",
 "endTime":"21:15",
 "duration":2700,
 "datetime":"2026-03-03",
 "dated":"TH3",
 "tvname":"Hải Phòng"},
 {"startTime":"21:15",
 "name":"An Ninh Hải Phòng: Cách Làm Hiệu Quả Vì Nhân Dân Phục Vụ",
 "link":"https://tv360.vn/tv?ch=60&d=2026-03-03&pid=13457256847&21:15+haiphong",
 "endTime":"21:35",
 "duration":1200,
 "datetime":"2026-03-03",
 "dated":"TH3",
 "tvname":"Hải Phòng"},
 {"startTime":"21:35",
 "name":"Phim Truyện Trung Quốc: Xứng Danh Anh Hùng (Tập 2)",
 "link":"https://tv360.vn/tv?ch=60&d=2026-03-03&pid=13457256850&21:35+haiphong",
 "endTime":"22:20",
 "duration":2700,
 "datetime":"2026-03-03",
 "dated":"TH3",
 "tvname":"Hải Phòng"},
 {"startTime":"22:20",
 "name":"Y Tế Sức Khỏe: Gia Tăng Bệnh Nhân Nhi Mắc Hô Hấp Nhập Viện",
 "link":"https://tv360.vn/tv?ch=60&d=2026-03-03&pid=13457256853&22:20+haiphong",
 "endTime":"22:40",
 "duration":1200,
 "datetime":"2026-03-03",
 "dated":"TH3",
 "tvname":"Hải Phòng"},
 {"startTime":"22:40",
 "name":"Bản Tin Thời Sự Cuối Ngày",
 "link":"https://tv360.vn/tv?ch=60&d=2026-03-03&pid=13457256856&22:40+haiphong",
 "endTime":"22:55",
 "duration":900,
 "datetime":"2026-03-03",
 "dated":"TH3",
 "tvname":"Hải Phòng"},
 {"startTime":"22:55",
 "name":"Thế Giới Mỗi Ngày",
 "link":"https://tv360.vn/tv?ch=60&d=2026-03-03&pid=13457256859&22:55+haiphong",
 "endTime":"23:05",
 "duration":600,
 "datetime":"2026-03-03",
 "dated":"TH3",
 "tvname":"Hải Phòng"},
 {"startTime":"23:05",
 "name":"Bản Tin Thời Sự Hải Phòng Bằng Tiếng Anh",
 "link":"https://tv360.vn/tv?ch=60&d=2026-03-03&pid=13457256862&23:05+haiphong",
 "endTime":"23:20",
 "duration":900,
 "datetime":"2026-03-03",
 "dated":"TH3",
 "tvname":"Hải Phòng"},
 {"startTime":"23:20",
 "name":"Bản Tin Thời Sự Hải Phòng Bằng Tiếng Trung Quốc",
 "link":"https://tv360.vn/tv?ch=60&d=2026-03-03&pid=13457256865&23:20+haiphong",
 "endTime":"23:35",
 "duration":900,
 "datetime":"2026-03-03",
 "dated":"TH3",
 "tvname":"Hải Phòng"},
 {"startTime":"23:35",
 "name":"Trên Khán Đài (Số 18)",
 "link":"https://tv360.vn/tv?ch=60&d=2026-03-03&pid=13457256868&23:35+haiphong",
 "endTime":"23:59",
 "duration":1499,
 "datetime":"2026-03-03",
 "dated":"TH3",
 "tvname":"Hải Phòng"}]