[{"startTime":"00:00",
 "name":"Con gái nhà vua",
 "link":"https://tv360.vn/tv?ch=228&d=2025-12-23&pid=13453335712&00:00+kactionsd",
 "endTime":"00:30",
 "duration":1800,
 "datetime":"2025-12-23",
 "dated":"TH3",
 "tvname":"K+ Action SD"},
 {"startTime":"00:30",
 "name":"Các cặp đôi Hollywood- Tập 651",
 "link":"https://tv360.vn/tv?ch=228&d=2025-12-23&pid=13453335715&00:30+kactionsd",
 "endTime":"01:00",
 "duration":1800,
 "datetime":"2025-12-23",
 "dated":"TH3",
 "tvname":"K+ Action SD"},
 {"startTime":"01:00",
 "name":"Đệm phát sóng",
 "link":"https://tv360.vn/tv?ch=228&d=2025-12-23&pid=13453335718&01:00+kactionsd",
 "endTime":"01:15",
 "duration":900,
 "datetime":"2025-12-23",
 "dated":"TH3",
 "tvname":"K+ Action SD"},
 {"startTime":"01:15",
 "name":"ACL Elite",
 "link":"https://tv360.vn/tv?ch=228&d=2025-12-23&pid=13453335721&01:15+kactionsd",
 "endTime":"01:45",
 "duration":1800,
 "datetime":"2025-12-23",
 "dated":"TH3",
 "tvname":"K+ Action SD"},
 {"startTime":"01:45",
 "name":"MD6",
 "link":"https://tv360.vn/tv?ch=228&d=2025-12-23&pid=13453335724&01:45+kactionsd",
 "endTime":"02:15",
 "duration":1800,
 "datetime":"2025-12-23",
 "dated":"TH3",
 "tvname":"K+ Action SD"},
 {"startTime":"02:15",
 "name":"AL GHARAFA",
 "link":"https://tv360.vn/tv?ch=228&d=2025-12-23&pid=13453335727&02:15+kactionsd",
 "endTime":"02:30",
 "duration":900,
 "datetime":"2025-12-23",
 "dated":"TH3",
 "tvname":"K+ Action SD"},
 {"startTime":"02:30",
 "name":"AL WAHDA",
 "link":"https://tv360.vn/tv?ch=228&d=2025-12-23&pid=13453335730&02:30+kactionsd",
 "endTime":"02:45",
 "duration":900,
 "datetime":"2025-12-23",
 "dated":"TH3",
 "tvname":"K+ Action SD"},
 {"startTime":"02:45",
 "name":"TUE 1H15",
 "link":"https://tv360.vn/tv?ch=228&d=2025-12-23&pid=13453335733&02:45+kactionsd",
 "endTime":"03:15",
 "duration":1800,
 "datetime":"2025-12-23",
 "dated":"TH3",
 "tvname":"K+ Action SD"},
 {"startTime":"03:15",
 "name":"Đệm phát sóng",
 "link":"https://tv360.vn/tv?ch=228&d=2025-12-23&pid=13453335736&03:15+kactionsd",
 "endTime":"03:30",
 "duration":900,
 "datetime":"2025-12-23",
 "dated":"TH3",
 "tvname":"K+ Action SD"},
 {"startTime":"03:30",
 "name":"Các cặp đôi Hollywood- Tập 653",
 "link":"https://tv360.vn/tv?ch=228&d=2025-12-23&pid=13453335739&03:30+kactionsd",
 "endTime":"04:00",
 "duration":1800,
 "datetime":"2025-12-23",
 "dated":"TH3",
 "tvname":"K+ Action SD"},
 {"startTime":"04:00",
 "name":"Ai là hung thủ- Tập 09",
 "link":"https://tv360.vn/tv?ch=228&d=2025-12-23&pid=13453335742&04:00+kactionsd",
 "endTime":"04:45",
 "duration":2700,
 "datetime":"2025-12-23",
 "dated":"TH3",
 "tvname":"K+ Action SD"},
 {"startTime":"04:45",
 "name":"Đệm phát sóng",
 "link":"https://tv360.vn/tv?ch=228&d=2025-12-23&pid=13453335745&04:45+kactionsd",
 "endTime":"05:00",
 "duration":900,
 "datetime":"2025-12-23",
 "dated":"TH3",
 "tvname":"K+ Action SD"},
 {"startTime":"05:00",
 "name":"Chuyện kinh hoàng đô thị- Tập 1-5",
 "link":"https://tv360.vn/tv?ch=228&d=2025-12-23&pid=13453335748&05:00+kactionsd",
 "endTime":"06:00",
 "duration":3600,
 "datetime":"2025-12-23",
 "dated":"TH3",
 "tvname":"K+ Action SD"},
 {"startTime":"06:00",
 "name":"Mất tích: Thế giới bên kia- Tập 11",
 "link":"https://tv360.vn/tv?ch=228&d=2025-12-23&pid=13453335751&06:00+kactionsd",
 "endTime":"06:45",
 "duration":2700,
 "datetime":"2025-12-23",
 "dated":"TH3",
 "tvname":"K+ Action SD"},
 {"startTime":"06:45",
 "name":"Đệm phát sóng",
 "link":"https://tv360.vn/tv?ch=228&d=2025-12-23&pid=13453335754&06:45+kactionsd",
 "endTime":"07:00",
 "duration":900,
 "datetime":"2025-12-23",
 "dated":"TH3",
 "tvname":"K+ Action SD"},
 {"startTime":"07:00",
 "name":"Quái vật Chimera- Tập 21",
 "link":"https://tv360.vn/tv?ch=228&d=2025-12-23&pid=13453335757&07:00+kactionsd",
 "endTime":"07:45",
 "duration":2700,
 "datetime":"2025-12-23",
 "dated":"TH3",
 "tvname":"K+ Action SD"},
 {"startTime":"07:45",
 "name":"Nạn nhân không hoàn hảo- Tập 17",
 "link":"https://tv360.vn/tv?ch=228&d=2025-12-23&pid=13453335760&07:45+kactionsd",
 "endTime":"08:30",
 "duration":2700,
 "datetime":"2025-12-23",
 "dated":"TH3",
 "tvname":"K+ Action SD"},
 {"startTime":"08:30",
 "name":"Nạn nhân không hoàn hảo- Tập 18",
 "link":"https://tv360.vn/tv?ch=228&d=2025-12-23&pid=13453335763&08:30+kactionsd",
 "endTime":"09:15",
 "duration":2700,
 "datetime":"2025-12-23",
 "dated":"TH3",
 "tvname":"K+ Action SD"},
 {"startTime":"09:15",
 "name":"Góa phụ Greta",
 "link":"https://tv360.vn/tv?ch=228&d=2025-12-23&pid=13453335766&09:15+kactionsd",
 "endTime":"11:00",
 "duration":6300,
 "datetime":"2025-12-23",
 "dated":"TH3",
 "tvname":"K+ Action SD"},
 {"startTime":"11:00",
 "name":"Chuyện kinh hoàng đô thị- Tập 1-5",
 "link":"https://tv360.vn/tv?ch=228&d=2025-12-23&pid=13453335769&11:00+kactionsd",
 "endTime":"12:00",
 "duration":3600,
 "datetime":"2025-12-23",
 "dated":"TH3",
 "tvname":"K+ Action SD"},
 {"startTime":"12:00",
 "name":"Quái vật Chimera- Tập 22",
 "link":"https://tv360.vn/tv?ch=228&d=2025-12-23&pid=13453335772&12:00+kactionsd",
 "endTime":"12:45",
 "duration":2700,
 "datetime":"2025-12-23",
 "dated":"TH3",
 "tvname":"K+ Action SD"},
 {"startTime":"12:45",
 "name":"Đệm phát sóng",
 "link":"https://tv360.vn/tv?ch=228&d=2025-12-23&pid=13453335775&12:45+kactionsd",
 "endTime":"13:00",
 "duration":900,
 "datetime":"2025-12-23",
 "dated":"TH3",
 "tvname":"K+ Action SD"},
 {"startTime":"13:00",
 "name":"Ai là hung thủ- Tập 10",
 "link":"https://tv360.vn/tv?ch=228&d=2025-12-23&pid=13453335778&13:00+kactionsd",
 "endTime":"13:45",
 "duration":2700,
 "datetime":"2025-12-23",
 "dated":"TH3",
 "tvname":"K+ Action SD"},
 {"startTime":"13:45",
 "name":"Đệm phát sóng",
 "link":"https://tv360.vn/tv?ch=228&d=2025-12-23&pid=13453335781&13:45+kactionsd",
 "endTime":"14:00",
 "duration":900,
 "datetime":"2025-12-23",
 "dated":"TH3",
 "tvname":"K+ Action SD"},
 {"startTime":"14:00",
 "name":"Mất tích: Thế giới bên kia- Tập 11",
 "link":"https://tv360.vn/tv?ch=228&d=2025-12-23&pid=13453335784&14:00+kactionsd",
 "endTime":"14:45",
 "duration":2700,
 "datetime":"2025-12-23",
 "dated":"TH3",
 "tvname":"K+ Action SD"},
 {"startTime":"14:45",
 "name":"Đệm phát sóng",
 "link":"https://tv360.vn/tv?ch=228&d=2025-12-23&pid=13453335787&14:45+kactionsd",
 "endTime":"15:00",
 "duration":900,
 "datetime":"2025-12-23",
 "dated":"TH3",
 "tvname":"K+ Action SD"},
 {"startTime":"15:00",
 "name":"Bão trắng 3: Thiên đàng hay địa ngục",
 "link":"https://tv360.vn/tv?ch=228&d=2025-12-23&pid=13453335790&15:00+kactionsd",
 "endTime":"17:00",
 "duration":7200,
 "datetime":"2025-12-23",
 "dated":"TH3",
 "tvname":"K+ Action SD"},
 {"startTime":"17:00",
 "name":"Quái vật Chimera- Tập 16",
 "link":"https://tv360.vn/tv?ch=228&d=2025-12-23&pid=13453385920&17:00+kactionsd",
 "endTime":"17:45",
 "duration":2700,
 "datetime":"2025-12-23",
 "dated":"TH3",
 "tvname":"K+ Action SD"},
 {"startTime":"17:45",
 "name":"Đệm phát sóng",
 "link":"https://tv360.vn/tv?ch=228&d=2025-12-23&pid=13453385923&17:45+kactionsd",
 "endTime":"18:00",
 "duration":900,
 "datetime":"2025-12-23",
 "dated":"TH3",
 "tvname":"K+ Action SD"},
 {"startTime":"18:00",
 "name":"Nhất Niệm Quan Sơn- Tập 37",
 "link":"https://tv360.vn/tv?ch=228&d=2025-12-23&pid=13453385926&18:00+kactionsd",
 "endTime":"18:45",
 "duration":2700,
 "datetime":"2025-12-23",
 "dated":"TH3",
 "tvname":"K+ Action SD"},
 {"startTime":"18:45",
 "name":"Đệm phát sóng",
 "link":"https://tv360.vn/tv?ch=228&d=2025-12-23&pid=13453385929&18:45+kactionsd",
 "endTime":"19:00",
 "duration":900,
 "datetime":"2025-12-23",
 "dated":"TH3",
 "tvname":"K+ Action SD"},
 {"startTime":"19:00",
 "name":"Mất tích: Thế giới bên kia- Tập 12",
 "link":"https://tv360.vn/tv?ch=228&d=2025-12-23&pid=13453385932&19:00+kactionsd",
 "endTime":"19:45",
 "duration":2700,
 "datetime":"2025-12-23",
 "dated":"TH3",
 "tvname":"K+ Action SD"},
 {"startTime":"19:45",
 "name":"Đệm phát sóng",
 "link":"https://tv360.vn/tv?ch=228&d=2025-12-23&pid=13453385935&19:45+kactionsd",
 "endTime":"20:00",
 "duration":900,
 "datetime":"2025-12-23",
 "dated":"TH3",
 "tvname":"K+ Action SD"},
 {"startTime":"20:00",
 "name":"(VOICE) Đại Phụng Đả Canh Nhân- Tập 38",
 "link":"https://tv360.vn/tv?ch=228&d=2025-12-23&pid=13453385938&20:00+kactionsd",
 "endTime":"20:45",
 "duration":2700,
 "datetime":"2025-12-23",
 "dated":"TH3",
 "tvname":"K+ Action SD"},
 {"startTime":"20:45",
 "name":"Đệm phát sóng",
 "link":"https://tv360.vn/tv?ch=228&d=2025-12-23&pid=13453385941&20:45+kactionsd",
 "endTime":"21:00",
 "duration":900,
 "datetime":"2025-12-23",
 "dated":"TH3",
 "tvname":"K+ Action SD"},
 {"startTime":"21:00",
 "name":"Nạn nhân không hoàn hảo- Tập 19",
 "link":"https://tv360.vn/tv?ch=228&d=2025-12-23&pid=13453385944&21:00+kactionsd",
 "endTime":"21:45",
 "duration":2700,
 "datetime":"2025-12-23",
 "dated":"TH3",
 "tvname":"K+ Action SD"},
 {"startTime":"21:45",
 "name":"Nạn nhân không hoàn hảo- Tập 20",
 "link":"https://tv360.vn/tv?ch=228&d=2025-12-23&pid=13453385947&21:45+kactionsd",
 "endTime":"22:30",
 "duration":2700,
 "datetime":"2025-12-23",
 "dated":"TH3",
 "tvname":"K+ Action SD"},
 {"startTime":"22:30",
 "name":"Đệm phát sóng",
 "link":"https://tv360.vn/tv?ch=228&d=2025-12-23&pid=13453385950&22:30+kactionsd",
 "endTime":"22:45",
 "duration":900,
 "datetime":"2025-12-23",
 "dated":"TH3",
 "tvname":"K+ Action SD"},
 {"startTime":"22:45",
 "name":"Vây Hãm Tại Đài Bắc",
 "link":"https://tv360.vn/tv?ch=228&d=2025-12-23&pid=13453385953&22:45+kactionsd",
 "endTime":"23:59",
 "duration":4499,
 "datetime":"2025-12-23",
 "dated":"TH3",
 "tvname":"K+ Action SD"}]