[{"startTime":"06:00",
 "name":"Quảng Trị ngày mới",
 "link":"https://tv360.vn/tv?ch=83&d=2025-12-26&pid=13453500889&06:00+quangtri",
 "endTime":"06:20",
 "duration":1200,
 "datetime":"2025-12-26",
 "dated":"Hôm qua",
 "tvname":"Quảng Trị"},
 {"startTime":"06:20",
 "name":"Phóng sự",
 "link":"https://tv360.vn/tv?ch=83&d=2025-12-26&pid=13453500892&06:20+quangtri",
 "endTime":"06:30",
 "duration":600,
 "datetime":"2025-12-26",
 "dated":"Hôm qua",
 "tvname":"Quảng Trị"},
 {"startTime":"06:30",
 "name":"Khuyến học- khuyến tài",
 "link":"https://tv360.vn/tv?ch=83&d=2025-12-26&pid=13453500895&06:30+quangtri",
 "endTime":"06:45",
 "duration":900,
 "datetime":"2025-12-26",
 "dated":"Hôm qua",
 "tvname":"Quảng Trị"},
 {"startTime":"06:45",
 "name":"Phim sitcom",
 "link":"https://tv360.vn/tv?ch=83&d=2025-12-26&pid=13453500898&06:45+quangtri",
 "endTime":"07:00",
 "duration":900,
 "datetime":"2025-12-26",
 "dated":"Hôm qua",
 "tvname":"Quảng Trị"},
 {"startTime":"07:00",
 "name":"Phim truyện",
 "link":"https://tv360.vn/tv?ch=83&d=2025-12-26&pid=13453500901&07:00+quangtri",
 "endTime":"07:45",
 "duration":2700,
 "datetime":"2025-12-26",
 "dated":"Hôm qua",
 "tvname":"Quảng Trị"},
 {"startTime":"07:45",
 "name":"Không gian xanh",
 "link":"https://tv360.vn/tv?ch=83&d=2025-12-26&pid=13453500904&07:45+quangtri",
 "endTime":"08:00",
 "duration":900,
 "datetime":"2025-12-26",
 "dated":"Hôm qua",
 "tvname":"Quảng Trị"},
 {"startTime":"08:00",
 "name":"Tọa đàm",
 "link":"https://tv360.vn/tv?ch=83&d=2025-12-26&pid=13453500907&08:00+quangtri",
 "endTime":"08:30",
 "duration":1800,
 "datetime":"2025-12-26",
 "dated":"Hôm qua",
 "tvname":"Quảng Trị"},
 {"startTime":"08:30",
 "name":"Tác phẩm mới",
 "link":"https://tv360.vn/tv?ch=83&d=2025-12-26&pid=13453500910&08:30+quangtri",
 "endTime":"08:45",
 "duration":900,
 "datetime":"2025-12-26",
 "dated":"Hôm qua",
 "tvname":"Quảng Trị"},
 {"startTime":"08:45",
 "name":"Nhịp sống trẻ",
 "link":"https://tv360.vn/tv?ch=83&d=2025-12-26&pid=13453500913&08:45+quangtri",
 "endTime":"09:00",
 "duration":900,
 "datetime":"2025-12-26",
 "dated":"Hôm qua",
 "tvname":"Quảng Trị"},
 {"startTime":"09:00",
 "name":"Tự tin để đẹp",
 "link":"https://tv360.vn/tv?ch=83&d=2025-12-26&pid=13453500916&09:00+quangtri",
 "endTime":"09:20",
 "duration":1200,
 "datetime":"2025-12-26",
 "dated":"Hôm qua",
 "tvname":"Quảng Trị"},
 {"startTime":"09:20",
 "name":"Phóng sự",
 "link":"https://tv360.vn/tv?ch=83&d=2025-12-26&pid=13453500919&09:20+quangtri",
 "endTime":"09:30",
 "duration":600,
 "datetime":"2025-12-26",
 "dated":"Hôm qua",
 "tvname":"Quảng Trị"},
 {"startTime":"09:30",
 "name":"Thời sự trực tiếp",
 "link":"https://tv360.vn/tv?ch=83&d=2025-12-26&pid=13453500922&09:30+quangtri",
 "endTime":"09:45",
 "duration":900,
 "datetime":"2025-12-26",
 "dated":"Hôm qua",
 "tvname":"Quảng Trị"},
 {"startTime":"09:45",
 "name":"Sức khỏe là vàng",
 "link":"https://tv360.vn/tv?ch=83&d=2025-12-26&pid=13453500925&09:45+quangtri",
 "endTime":"10:30",
 "duration":2700,
 "datetime":"2025-12-26",
 "dated":"Hôm qua",
 "tvname":"Quảng Trị"},
 {"startTime":"10:30",
 "name":"Ca nhạc quốc tế",
 "link":"https://tv360.vn/tv?ch=83&d=2025-12-26&pid=13453500928&10:30+quangtri",
 "endTime":"11:00",
 "duration":1800,
 "datetime":"2025-12-26",
 "dated":"Hôm qua",
 "tvname":"Quảng Trị"},
 {"startTime":"11:00",
 "name":"Với khán giả xem truyền hình",
 "link":"https://tv360.vn/tv?ch=83&d=2025-12-26&pid=13453500931&11:00+quangtri",
 "endTime":"11:15",
 "duration":900,
 "datetime":"2025-12-26",
 "dated":"Hôm qua",
 "tvname":"Quảng Trị"},
 {"startTime":"11:15",
 "name":"Thiếu nhi Quảng Trị",
 "link":"https://tv360.vn/tv?ch=83&d=2025-12-26&pid=13453500934&11:15+quangtri",
 "endTime":"11:30",
 "duration":900,
 "datetime":"2025-12-26",
 "dated":"Hôm qua",
 "tvname":"Quảng Trị"},
 {"startTime":"11:30",
 "name":"Thời sự",
 "link":"https://tv360.vn/tv?ch=83&d=2025-12-26&pid=13453500937&11:30+quangtri",
 "endTime":"12:00",
 "duration":1800,
 "datetime":"2025-12-26",
 "dated":"Hôm qua",
 "tvname":"Quảng Trị"},
 {"startTime":"12:00",
 "name":"Phim truyện",
 "link":"https://tv360.vn/tv?ch=83&d=2025-12-26&pid=13453500940&12:00+quangtri",
 "endTime":"12:45",
 "duration":2700,
 "datetime":"2025-12-26",
 "dated":"Hôm qua",
 "tvname":"Quảng Trị"},
 {"startTime":"12:45",
 "name":"Về chốn linh thiêng",
 "link":"https://tv360.vn/tv?ch=83&d=2025-12-26&pid=13453500943&12:45+quangtri",
 "endTime":"13:00",
 "duration":900,
 "datetime":"2025-12-26",
 "dated":"Hôm qua",
 "tvname":"Quảng Trị"},
 {"startTime":"13:00",
 "name":"Sức khỏe của bạn",
 "link":"https://tv360.vn/tv?ch=83&d=2025-12-26&pid=13453500946&13:00+quangtri",
 "endTime":"13:15",
 "duration":900,
 "datetime":"2025-12-26",
 "dated":"Hôm qua",
 "tvname":"Quảng Trị"},
 {"startTime":"13:15",
 "name":"Mỗi tuần một chuyện",
 "link":"https://tv360.vn/tv?ch=83&d=2025-12-26&pid=13453500949&13:15+quangtri",
 "endTime":"13:25",
 "duration":600,
 "datetime":"2025-12-26",
 "dated":"Hôm qua",
 "tvname":"Quảng Trị"},
 {"startTime":"13:25",
 "name":"Nhịp cầu nhân ái",
 "link":"https://tv360.vn/tv?ch=83&d=2025-12-26&pid=13453500952&13:25+quangtri",
 "endTime":"13:35",
 "duration":600,
 "datetime":"2025-12-26",
 "dated":"Hôm qua",
 "tvname":"Quảng Trị"},
 {"startTime":"13:35",
 "name":"Ký sự",
 "link":"https://tv360.vn/tv?ch=83&d=2025-12-26&pid=13453500955&13:35+quangtri",
 "endTime":"13:50",
 "duration":900,
 "datetime":"2025-12-26",
 "dated":"Hôm qua",
 "tvname":"Quảng Trị"},
 {"startTime":"13:50",
 "name":"Nội chính- phòng- chống tham nhũng- lãng phí và tiêu cực",
 "link":"https://tv360.vn/tv?ch=83&d=2025-12-26&pid=13453500958&13:50+quangtri",
 "endTime":"14:00",
 "duration":600,
 "datetime":"2025-12-26",
 "dated":"Hôm qua",
 "tvname":"Quảng Trị"},
 {"startTime":"14:00",
 "name":"Vì Quảng Trị phát triển",
 "link":"https://tv360.vn/tv?ch=83&d=2025-12-26&pid=13453500961&14:00+quangtri",
 "endTime":"14:15",
 "duration":900,
 "datetime":"2025-12-26",
 "dated":"Hôm qua",
 "tvname":"Quảng Trị"},
 {"startTime":"14:15",
 "name":"Phóng sự",
 "link":"https://tv360.vn/tv?ch=83&d=2025-12-26&pid=13453500964&14:15+quangtri",
 "endTime":"14:30",
 "duration":900,
 "datetime":"2025-12-26",
 "dated":"Hôm qua",
 "tvname":"Quảng Trị"},
 {"startTime":"14:30",
 "name":"Những câu chuyện thú vị",
 "link":"https://tv360.vn/tv?ch=83&d=2025-12-26&pid=13453500967&14:30+quangtri",
 "endTime":"15:00",
 "duration":1800,
 "datetime":"2025-12-26",
 "dated":"Hôm qua",
 "tvname":"Quảng Trị"},
 {"startTime":"15:00",
 "name":"Phim truyện",
 "link":"https://tv360.vn/tv?ch=83&d=2025-12-26&pid=13453500970&15:00+quangtri",
 "endTime":"15:45",
 "duration":2700,
 "datetime":"2025-12-26",
 "dated":"Hôm qua",
 "tvname":"Quảng Trị"},
 {"startTime":"15:45",
 "name":"Thiếu nhi Quảng Trị",
 "link":"https://tv360.vn/tv?ch=83&d=2025-12-26&pid=13453500973&15:45+quangtri",
 "endTime":"16:00",
 "duration":900,
 "datetime":"2025-12-26",
 "dated":"Hôm qua",
 "tvname":"Quảng Trị"},
 {"startTime":"16:00",
 "name":"Gõ cửa thăm nhà",
 "link":"https://tv360.vn/tv?ch=83&d=2025-12-26&pid=13453500976&16:00+quangtri",
 "endTime":"16:30",
 "duration":1800,
 "datetime":"2025-12-26",
 "dated":"Hôm qua",
 "tvname":"Quảng Trị"},
 {"startTime":"16:30",
 "name":"Cuộc sống muôn loài",
 "link":"https://tv360.vn/tv?ch=83&d=2025-12-26&pid=13453500979&16:30+quangtri",
 "endTime":"17:00",
 "duration":1800,
 "datetime":"2025-12-26",
 "dated":"Hôm qua",
 "tvname":"Quảng Trị"},
 {"startTime":"17:00",
 "name":"Thời sự trực tiếp",
 "link":"https://tv360.vn/tv?ch=83&d=2025-12-26&pid=13453500982&17:00+quangtri",
 "endTime":"17:15",
 "duration":900,
 "datetime":"2025-12-26",
 "dated":"Hôm qua",
 "tvname":"Quảng Trị"},
 {"startTime":"17:15",
 "name":"Phim truyện",
 "link":"https://tv360.vn/tv?ch=83&d=2025-12-26&pid=13453500985&17:15+quangtri",
 "endTime":"18:00",
 "duration":2700,
 "datetime":"2025-12-26",
 "dated":"Hôm qua",
 "tvname":"Quảng Trị"},
 {"startTime":"18:00",
 "name":"Phim sitcom: Soái ca anh ở đâu - Tập 86",
 "link":"https://tv360.vn/tv?ch=83&d=2025-12-26&pid=13453630951&18:00+quangtri",
 "endTime":"18:10",
 "duration":600,
 "datetime":"2025-12-26",
 "dated":"Hôm qua",
 "tvname":"Quảng Trị"},
 {"startTime":"18:10",
 "name":"Tọa đàm: Khoa học- công nghệ mở đường cho tăng trưởng",
 "link":"https://tv360.vn/tv?ch=83&d=2025-12-26&pid=13453630954&18:10+quangtri",
 "endTime":"18:40",
 "duration":1800,
 "datetime":"2025-12-26",
 "dated":"Hôm qua",
 "tvname":"Quảng Trị"},
 {"startTime":"18:40",
 "name":"24h.TV",
 "link":"https://tv360.vn/tv?ch=83&d=2025-12-26&pid=13453630957&18:40+quangtri",
 "endTime":"19:00",
 "duration":1200,
 "datetime":"2025-12-26",
 "dated":"Hôm qua",
 "tvname":"Quảng Trị"},
 {"startTime":"19:00",
 "name":"Tiếp sóng thời sự VTV",
 "link":"https://tv360.vn/tv?ch=83&d=2025-12-26&pid=13453630960&19:00+quangtri",
 "endTime":"19:45",
 "duration":2700,
 "datetime":"2025-12-26",
 "dated":"Hôm qua",
 "tvname":"Quảng Trị"},
 {"startTime":"19:45",
 "name":"Thời sự QTTV",
 "link":"https://tv360.vn/tv?ch=83&d=2025-12-26&pid=13453630963&19:45+quangtri",
 "endTime":"20:15",
 "duration":1800,
 "datetime":"2025-12-26",
 "dated":"Hôm qua",
 "tvname":"Quảng Trị"},
 {"startTime":"20:15",
 "name":"Chuyên đề khoa giáo: Nuôi gà Ri lai - hướng mở sinh kế cho đồng bào gắn với phát triển du lịch",
 "link":"https://tv360.vn/tv?ch=83&d=2025-12-26&pid=13453630966&20:15+quangtri",
 "endTime":"20:25",
 "duration":600,
 "datetime":"2025-12-26",
 "dated":"Hôm qua",
 "tvname":"Quảng Trị"},
 {"startTime":"20:25",
 "name":"Nội chính- phòng chống tham nhũng- lãng phí và tiêu cực",
 "link":"https://tv360.vn/tv?ch=83&d=2025-12-26&pid=13453630969&20:25+quangtri",
 "endTime":"20:35",
 "duration":600,
 "datetime":"2025-12-26",
 "dated":"Hôm qua",
 "tvname":"Quảng Trị"},
 {"startTime":"20:35",
 "name":"Phóng sự: Trung tâm lưu trữ lịch sử Nam Quảng Trị - Hành trình lưu giữ ký ức",
 "link":"https://tv360.vn/tv?ch=83&d=2025-12-26&pid=13453630972&20:35+quangtri",
 "endTime":"20:50",
 "duration":900,
 "datetime":"2025-12-26",
 "dated":"Hôm qua",
 "tvname":"Quảng Trị"},
 {"startTime":"20:50",
 "name":"Phim truyện: Gia đình võ thuật - Tập 22",
 "link":"https://tv360.vn/tv?ch=83&d=2025-12-26&pid=13453630975&20:50+quangtri",
 "endTime":"21:35",
 "duration":2700,
 "datetime":"2025-12-26",
 "dated":"Hôm qua",
 "tvname":"Quảng Trị"},
 {"startTime":"21:35",
 "name":"Tự tin để đẹp",
 "link":"https://tv360.vn/tv?ch=83&d=2025-12-26&pid=13453630978&21:35+quangtri",
 "endTime":"21:55",
 "duration":1200,
 "datetime":"2025-12-26",
 "dated":"Hôm qua",
 "tvname":"Quảng Trị"},
 {"startTime":"21:55",
 "name":"Phóng sự: Gỡ khó cho bài toán lao động ngành may",
 "link":"https://tv360.vn/tv?ch=83&d=2025-12-26&pid=13453630981&21:55+quangtri",
 "endTime":"22:10",
 "duration":900,
 "datetime":"2025-12-26",
 "dated":"Hôm qua",
 "tvname":"Quảng Trị"},
 {"startTime":"22:10",
 "name":"Tọa đàm: Khoa học- công nghệ mở đường cho tăng trưởng",
 "link":"https://tv360.vn/tv?ch=83&d=2025-12-26&pid=13453630984&22:10+quangtri",
 "endTime":"22:40",
 "duration":1800,
 "datetime":"2025-12-26",
 "dated":"Hôm qua",
 "tvname":"Quảng Trị"},
 {"startTime":"22:40",
 "name":"Ca nhạc: Bài ca người lính",
 "link":"https://tv360.vn/tv?ch=83&d=2025-12-26&pid=13453630987&22:40+quangtri",
 "endTime":"23:59",
 "duration":4799,
 "datetime":"2025-12-26",
 "dated":"Hôm qua",
 "tvname":"Quảng Trị"}]