[{"startTime":"00:00",
 "name":"Không Có Chương Trình",
 "link":"https://tv360.vn/tv?ch=9868&d=2026-01-14&pid=13454626900&00:00+tv360+6",
 "endTime":"00:05",
 "duration":300,
 "datetime":"2026-01-14",
 "dated":"TH4",
 "tvname":"TV360+ 6"},
 {"startTime":"00:30",
 "name":"THTT Vòng 17 Bundesliga 2025/26: Stuttgart vs Eintracht Frankfurt",
 "link":"https://tv360.vn/tv?ch=9868&d=2026-01-14&pid=13454626903&00:30+tv360+6",
 "endTime":"02:30",
 "duration":7200,
 "datetime":"2026-01-14",
 "dated":"TH4",
 "tvname":"TV360+ 6"}]