[{"startTime":"00:00",
 "name":"Tài Tiểu Tuyệt - Mùa 6 - Tập 68",
 "link":"https://tv360.vn/tv?ch=180&d=2025-12-19&pid=13453111069&00:00+cab1enter",
 "endTime":"01:00",
 "duration":3600,
 "datetime":"2025-12-19",
 "dated":"TH6",
 "tvname":"VTVcab 1 - Vie Giải Trí HD"},
 {"startTime":"01:00",
 "name":"Congo - Di Sản Cuối Cùng Của Hành Tinh Xanh - Tập 6",
 "link":"https://tv360.vn/tv?ch=180&d=2025-12-19&pid=13453111072&01:00+cab1enter",
 "endTime":"01:30",
 "duration":1800,
 "datetime":"2025-12-19",
 "dated":"TH6",
 "tvname":"VTVcab 1 - Vie Giải Trí HD"},
 {"startTime":"01:30",
 "name":"Ai Là Số 1? Tập 9 Phần 1",
 "link":"https://tv360.vn/tv?ch=180&d=2025-12-19&pid=13453111075&01:30+cab1enter",
 "endTime":"02:30",
 "duration":3600,
 "datetime":"2025-12-19",
 "dated":"TH6",
 "tvname":"VTVcab 1 - Vie Giải Trí HD"},
 {"startTime":"02:30",
 "name":"Những Đứa Con Trời Ban - Tập 664",
 "link":"https://tv360.vn/tv?ch=180&d=2025-12-19&pid=13453111078&02:30+cab1enter",
 "endTime":"03:30",
 "duration":3600,
 "datetime":"2025-12-19",
 "dated":"TH6",
 "tvname":"VTVcab 1 - Vie Giải Trí HD"},
 {"startTime":"03:30",
 "name":"Ai Cũng Bật Cười - Tập 6",
 "link":"https://tv360.vn/tv?ch=180&d=2025-12-19&pid=13453111081&03:30+cab1enter",
 "endTime":"04:30",
 "duration":3600,
 "datetime":"2025-12-19",
 "dated":"TH6",
 "tvname":"VTVcab 1 - Vie Giải Trí HD"},
 {"startTime":"04:30",
 "name":"Amur Kỳ Bí - Tập 4",
 "link":"https://tv360.vn/tv?ch=180&d=2025-12-19&pid=13453111084&04:30+cab1enter",
 "endTime":"05:00",
 "duration":1800,
 "datetime":"2025-12-19",
 "dated":"TH6",
 "tvname":"VTVcab 1 - Vie Giải Trí HD"},
 {"startTime":"05:00",
 "name":"Kiến Tạo Nhịp Cầu - Mùa 10 - Tập 11",
 "link":"https://tv360.vn/tv?ch=180&d=2025-12-19&pid=13453111087&05:00+cab1enter",
 "endTime":"06:00",
 "duration":3600,
 "datetime":"2025-12-19",
 "dated":"TH6",
 "tvname":"VTVcab 1 - Vie Giải Trí HD"},
 {"startTime":"06:00",
 "name":"Siêu Trí Tuệ Việt Nam - Mùa 2 - Tập 10 - Phần 1",
 "link":"https://tv360.vn/tv?ch=180&d=2025-12-19&pid=13453111090&06:00+cab1enter",
 "endTime":"07:00",
 "duration":3600,
 "datetime":"2025-12-19",
 "dated":"TH6",
 "tvname":"VTVcab 1 - Vie Giải Trí HD"},
 {"startTime":"07:00",
 "name":"Giấc Mơ Của Mẹ - Tập 15",
 "link":"https://tv360.vn/tv?ch=180&d=2025-12-19&pid=13453111093&07:00+cab1enter",
 "endTime":"08:00",
 "duration":3600,
 "datetime":"2025-12-19",
 "dated":"TH6",
 "tvname":"VTVcab 1 - Vie Giải Trí HD"},
 {"startTime":"08:00",
 "name":"Tân Thiên Long Bát Bộ 2021 - Tập 17",
 "link":"https://tv360.vn/tv?ch=180&d=2025-12-19&pid=13453111096&08:00+cab1enter",
 "endTime":"09:00",
 "duration":3600,
 "datetime":"2025-12-19",
 "dated":"TH6",
 "tvname":"VTVcab 1 - Vie Giải Trí HD"},
 {"startTime":"09:00",
 "name":"Tài Tiểu Tuyệt - Mùa 6 - Tập 68",
 "link":"https://tv360.vn/tv?ch=180&d=2025-12-19&pid=13453111099&09:00+cab1enter",
 "endTime":"10:00",
 "duration":3600,
 "datetime":"2025-12-19",
 "dated":"TH6",
 "tvname":"VTVcab 1 - Vie Giải Trí HD"},
 {"startTime":"10:00",
 "name":"Hãy Gọi Anh Là Sếp - Tập 7",
 "link":"https://tv360.vn/tv?ch=180&d=2025-12-19&pid=13453139320&10:00+cab1enter",
 "endTime":"11:00",
 "duration":3600,
 "datetime":"2025-12-19",
 "dated":"TH6",
 "tvname":"VTVcab 1 - Vie Giải Trí HD"},
 {"startTime":"11:00",
 "name":"Hoán Đổi Con Cưng - Tập 1",
 "link":"https://tv360.vn/tv?ch=180&d=2025-12-19&pid=13453139323&11:00+cab1enter",
 "endTime":"12:00",
 "duration":3600,
 "datetime":"2025-12-19",
 "dated":"TH6",
 "tvname":"VTVcab 1 - Vie Giải Trí HD"},
 {"startTime":"12:00",
 "name":"Chiếc Bật Lửa Và Váy Công Chúa - Tập 23",
 "link":"https://tv360.vn/tv?ch=180&d=2025-12-19&pid=13453139326&12:00+cab1enter",
 "endTime":"13:00",
 "duration":3600,
 "datetime":"2025-12-19",
 "dated":"TH6",
 "tvname":"VTVcab 1 - Vie Giải Trí HD"},
 {"startTime":"13:00",
 "name":"Giấc Mơ Của Mẹ - Tập 16",
 "link":"https://tv360.vn/tv?ch=180&d=2025-12-19&pid=13453139329&13:00+cab1enter",
 "endTime":"14:00",
 "duration":3600,
 "datetime":"2025-12-19",
 "dated":"TH6",
 "tvname":"VTVcab 1 - Vie Giải Trí HD"},
 {"startTime":"14:00",
 "name":"Những Đứa Con Trời Ban - Tập 665",
 "link":"https://tv360.vn/tv?ch=180&d=2025-12-19&pid=13453139332&14:00+cab1enter",
 "endTime":"15:00",
 "duration":3600,
 "datetime":"2025-12-19",
 "dated":"TH6",
 "tvname":"VTVcab 1 - Vie Giải Trí HD"},
 {"startTime":"15:00",
 "name":"Hoán Đổi Con Cưng - Tập 1",
 "link":"https://tv360.vn/tv?ch=180&d=2025-12-19&pid=13453139335&15:00+cab1enter",
 "endTime":"16:20",
 "duration":4800,
 "datetime":"2025-12-19",
 "dated":"TH6",
 "tvname":"VTVcab 1 - Vie Giải Trí HD"},
 {"startTime":"16:20",
 "name":"Vị Giác Tình Yêu - Tập 14",
 "link":"https://tv360.vn/tv?ch=180&d=2025-12-19&pid=13453173163&16:20+cab1enter",
 "endTime":"17:00",
 "duration":2400,
 "datetime":"2025-12-19",
 "dated":"TH6",
 "tvname":"VTVcab 1 - Vie Giải Trí HD"},
 {"startTime":"17:00",
 "name":"Hãy Gọi Anh Là Sếp - Tập 8",
 "link":"https://tv360.vn/tv?ch=180&d=2025-12-19&pid=13453295749&17:00+cab1enter",
 "endTime":"18:00",
 "duration":3600,
 "datetime":"2025-12-19",
 "dated":"TH6",
 "tvname":"VTVcab 1 - Vie Giải Trí HD"},
 {"startTime":"18:00",
 "name":"Tân Thiên Long Bát Bộ 2021 - Tập 18",
 "link":"https://tv360.vn/tv?ch=180&d=2025-12-19&pid=13453295752&18:00+cab1enter",
 "endTime":"19:00",
 "duration":3600,
 "datetime":"2025-12-19",
 "dated":"TH6",
 "tvname":"VTVcab 1 - Vie Giải Trí HD"},
 {"startTime":"19:00",
 "name":"Mật Mã Bí Ẩn - Tập 9",
 "link":"https://tv360.vn/tv?ch=180&d=2025-12-19&pid=13453295755&19:00+cab1enter",
 "endTime":"20:00",
 "duration":3600,
 "datetime":"2025-12-19",
 "dated":"TH6",
 "tvname":"VTVcab 1 - Vie Giải Trí HD"},
 {"startTime":"20:00",
 "name":"Song Hoa Hỷ Sự - Tập 23",
 "link":"https://tv360.vn/tv?ch=180&d=2025-12-19&pid=13453295758&20:00+cab1enter",
 "endTime":"21:30",
 "duration":5400,
 "datetime":"2025-12-19",
 "dated":"TH6",
 "tvname":"VTVcab 1 - Vie Giải Trí HD"},
 {"startTime":"21:30",
 "name":"Giày Đỏ - Tập 49",
 "link":"https://tv360.vn/tv?ch=180&d=2025-12-19&pid=13453295761&21:30+cab1enter",
 "endTime":"22:00",
 "duration":1800,
 "datetime":"2025-12-19",
 "dated":"TH6",
 "tvname":"VTVcab 1 - Vie Giải Trí HD"},
 {"startTime":"22:00",
 "name":"Giấc Mơ Của Mẹ - Tập 17",
 "link":"https://tv360.vn/tv?ch=180&d=2025-12-19&pid=13453295764&22:00+cab1enter",
 "endTime":"23:00",
 "duration":3600,
 "datetime":"2025-12-19",
 "dated":"TH6",
 "tvname":"VTVcab 1 - Vie Giải Trí HD"},
 {"startTime":"23:00",
 "name":"Ai Cũng Bật Cười - Tập 6",
 "link":"https://tv360.vn/tv?ch=180&d=2025-12-19&pid=13453295767&23:00+cab1enter",
 "endTime":"23:59",
 "duration":3599,
 "datetime":"2025-12-19",
 "dated":"TH6",
 "tvname":"VTVcab 1 - Vie Giải Trí HD"}]