[{"startTime":"00:00",
 "name":"Dòng Sông Huynh Đệ - Tập 57",
 "link":"https://tv360.vn/tv?ch=177&d=2025-11-28&pid=13451915473&00:00+cab19dram",
 "endTime":"00:30",
 "duration":1800,
 "datetime":"2025-11-28",
 "dated":"Hôm nay",
 "tvname":"VTVcab19 – Vie Dramas"},
 {"startTime":"00:30",
 "name":"Sống Cùng Viedramas 2024 - Tập 24",
 "link":"https://tv360.vn/tv?ch=177&d=2025-11-28&pid=13451915476&00:30+cab19dram",
 "endTime":"01:00",
 "duration":1800,
 "datetime":"2025-11-28",
 "dated":"Hôm nay",
 "tvname":"VTVcab19 – Vie Dramas"},
 {"startTime":"01:00",
 "name":"Nguyệt Ca Hành - Tập 20",
 "link":"https://tv360.vn/tv?ch=177&d=2025-11-28&pid=13451915479&01:00+cab19dram",
 "endTime":"02:00",
 "duration":3600,
 "datetime":"2025-11-28",
 "dated":"Hôm nay",
 "tvname":"VTVcab19 – Vie Dramas"},
 {"startTime":"02:00",
 "name":"Dòng Sông Huynh Đệ - Tập 58",
 "link":"https://tv360.vn/tv?ch=177&d=2025-11-28&pid=13451915482&02:00+cab19dram",
 "endTime":"03:00",
 "duration":3600,
 "datetime":"2025-11-28",
 "dated":"Hôm nay",
 "tvname":"VTVcab19 – Vie Dramas"},
 {"startTime":"03:00",
 "name":"Hoa Nở Nhớ Trăng - Tập 3",
 "link":"https://tv360.vn/tv?ch=177&d=2025-11-28&pid=13451915485&03:00+cab19dram",
 "endTime":"03:30",
 "duration":1800,
 "datetime":"2025-11-28",
 "dated":"Hôm nay",
 "tvname":"VTVcab19 – Vie Dramas"},
 {"startTime":"03:30",
 "name":"Sống Cùng Viedramas 2024 - Tập 24",
 "link":"https://tv360.vn/tv?ch=177&d=2025-11-28&pid=13451915488&03:30+cab19dram",
 "endTime":"04:00",
 "duration":1800,
 "datetime":"2025-11-28",
 "dated":"Hôm nay",
 "tvname":"VTVcab19 – Vie Dramas"},
 {"startTime":"04:00",
 "name":"Dòng Sông Huynh Đệ - Tập 59",
 "link":"https://tv360.vn/tv?ch=177&d=2025-11-28&pid=13451915491&04:00+cab19dram",
 "endTime":"05:00",
 "duration":3600,
 "datetime":"2025-11-28",
 "dated":"Hôm nay",
 "tvname":"VTVcab19 – Vie Dramas"},
 {"startTime":"05:00",
 "name":"Mật Mã Bí Ẩn - Tập 19",
 "link":"https://tv360.vn/tv?ch=177&d=2025-11-28&pid=13451915494&05:00+cab19dram",
 "endTime":"06:00",
 "duration":3600,
 "datetime":"2025-11-28",
 "dated":"Hôm nay",
 "tvname":"VTVcab19 – Vie Dramas"},
 {"startTime":"06:00",
 "name":"Dòng Sông Huynh Đệ - Tập 60",
 "link":"https://tv360.vn/tv?ch=177&d=2025-11-28&pid=13451915497&06:00+cab19dram",
 "endTime":"07:00",
 "duration":3600,
 "datetime":"2025-11-28",
 "dated":"Hôm nay",
 "tvname":"VTVcab19 – Vie Dramas"},
 {"startTime":"07:00",
 "name":"Nguyệt Ca Hành - Tập 21",
 "link":"https://tv360.vn/tv?ch=177&d=2025-11-28&pid=13451915500&07:00+cab19dram",
 "endTime":"08:00",
 "duration":3600,
 "datetime":"2025-11-28",
 "dated":"Hôm nay",
 "tvname":"VTVcab19 – Vie Dramas"},
 {"startTime":"08:00",
 "name":"Hoa Nở Nhớ Trăng - Tập 4",
 "link":"https://tv360.vn/tv?ch=177&d=2025-11-28&pid=13451915503&08:00+cab19dram",
 "endTime":"09:00",
 "duration":3600,
 "datetime":"2025-11-28",
 "dated":"Hôm nay",
 "tvname":"VTVcab19 – Vie Dramas"},
 {"startTime":"09:00",
 "name":"Chỉ Có Thể Là Tình Yêu - Tập 34",
 "link":"https://tv360.vn/tv?ch=177&d=2025-11-28&pid=13451915506&09:00+cab19dram",
 "endTime":"10:00",
 "duration":3600,
 "datetime":"2025-11-28",
 "dated":"Hôm nay",
 "tvname":"VTVcab19 – Vie Dramas"},
 {"startTime":"10:00",
 "name":"Nguyệt Ca Hành - Tập 22",
 "link":"https://tv360.vn/tv?ch=177&d=2025-11-28&pid=13451915509&10:00+cab19dram",
 "endTime":"11:00",
 "duration":3600,
 "datetime":"2025-11-28",
 "dated":"Hôm nay",
 "tvname":"VTVcab19 – Vie Dramas"},
 {"startTime":"11:00",
 "name":"Mật Mã Bí Ẩn - Tập 20",
 "link":"https://tv360.vn/tv?ch=177&d=2025-11-28&pid=13451915512&11:00+cab19dram",
 "endTime":"12:00",
 "duration":3600,
 "datetime":"2025-11-28",
 "dated":"Hôm nay",
 "tvname":"VTVcab19 – Vie Dramas"},
 {"startTime":"12:00",
 "name":"Hoa Nở Nhớ Trăng - Tập 5",
 "link":"https://tv360.vn/tv?ch=177&d=2025-11-28&pid=13451915515&12:00+cab19dram",
 "endTime":"13:00",
 "duration":3600,
 "datetime":"2025-11-28",
 "dated":"Hôm nay",
 "tvname":"VTVcab19 – Vie Dramas"},
 {"startTime":"13:00",
 "name":"Chỉ Có Thể Là Tình Yêu - Tập 35",
 "link":"https://tv360.vn/tv?ch=177&d=2025-11-28&pid=13451915518&13:00+cab19dram",
 "endTime":"14:00",
 "duration":3600,
 "datetime":"2025-11-28",
 "dated":"Hôm nay",
 "tvname":"VTVcab19 – Vie Dramas"},
 {"startTime":"14:00",
 "name":"Sự Hoàn Hảo Đáng Thương - Tập 16",
 "link":"https://tv360.vn/tv?ch=177&d=2025-11-28&pid=13451915521&14:00+cab19dram",
 "endTime":"15:00",
 "duration":3600,
 "datetime":"2025-11-28",
 "dated":"Hôm nay",
 "tvname":"VTVcab19 – Vie Dramas"},
 {"startTime":"15:00",
 "name":"Dòng Sông Huynh Đệ - Tập 61",
 "link":"https://tv360.vn/tv?ch=177&d=2025-11-28&pid=13451915524&15:00+cab19dram",
 "endTime":"16:00",
 "duration":3600,
 "datetime":"2025-11-28",
 "dated":"Hôm nay",
 "tvname":"VTVcab19 – Vie Dramas"},
 {"startTime":"16:00",
 "name":"Chỉ Có Thể Là Tình Yêu - Tập 36",
 "link":"https://tv360.vn/tv?ch=177&d=2025-11-28&pid=13451915527&16:00+cab19dram",
 "endTime":"17:00",
 "duration":3600,
 "datetime":"2025-11-28",
 "dated":"Hôm nay",
 "tvname":"VTVcab19 – Vie Dramas"},
 {"startTime":"17:00",
 "name":"Mật Mã Bí Ẩn - Tập 21",
 "link":"https://tv360.vn/tv?ch=177&d=2025-11-28&pid=13451915530&17:00+cab19dram",
 "endTime":"18:00",
 "duration":3600,
 "datetime":"2025-11-28",
 "dated":"Hôm nay",
 "tvname":"VTVcab19 – Vie Dramas"},
 {"startTime":"18:00",
 "name":"Sự Hoàn Hảo Đáng Thương - Tập 17",
 "link":"https://tv360.vn/tv?ch=177&d=2025-11-28&pid=13451915533&18:00+cab19dram",
 "endTime":"19:00",
 "duration":3600,
 "datetime":"2025-11-28",
 "dated":"Hôm nay",
 "tvname":"VTVcab19 – Vie Dramas"},
 {"startTime":"19:00",
 "name":"Nguyệt Ca Hành - Tập 23",
 "link":"https://tv360.vn/tv?ch=177&d=2025-11-28&pid=13451915536&19:00+cab19dram",
 "endTime":"20:00",
 "duration":3600,
 "datetime":"2025-11-28",
 "dated":"Hôm nay",
 "tvname":"VTVcab19 – Vie Dramas"},
 {"startTime":"20:00",
 "name":"Mật Mã Bí Ẩn - Tập 22",
 "link":"https://tv360.vn/tv?ch=177&d=2025-11-28&pid=13451915539&20:00+cab19dram",
 "endTime":"21:00",
 "duration":3600,
 "datetime":"2025-11-28",
 "dated":"Hôm nay",
 "tvname":"VTVcab19 – Vie Dramas"},
 {"startTime":"21:00",
 "name":"Chỉ Có Thể Là Tình Yêu - Tập 37",
 "link":"https://tv360.vn/tv?ch=177&d=2025-11-28&pid=13451915542&21:00+cab19dram",
 "endTime":"22:00",
 "duration":3600,
 "datetime":"2025-11-28",
 "dated":"Hôm nay",
 "tvname":"VTVcab19 – Vie Dramas"},
 {"startTime":"22:00",
 "name":"Sự Hoàn Hảo Đáng Thương - Tập 18",
 "link":"https://tv360.vn/tv?ch=177&d=2025-11-28&pid=13451915545&22:00+cab19dram",
 "endTime":"23:00",
 "duration":3600,
 "datetime":"2025-11-28",
 "dated":"Hôm nay",
 "tvname":"VTVcab19 – Vie Dramas"},
 {"startTime":"23:00",
 "name":"Hoa Nở Nhớ Trăng - Tập 5",
 "link":"https://tv360.vn/tv?ch=177&d=2025-11-28&pid=13451915548&23:00+cab19dram",
 "endTime":"23:59",
 "duration":3599,
 "datetime":"2025-11-28",
 "dated":"Hôm nay",
 "tvname":"VTVcab19 – Vie Dramas"}]