[{"startTime":"00:00",
 "name":"Phim Việt Nam: Một đời giông tố - Tập 7- 8",
 "link":"https://tv360.vn/tv?ch=219&d=2025-12-05&pid=13452405163&00:00+vinhlong3",
 "endTime":"01:50",
 "duration":6600,
 "datetime":"2025-12-05",
 "dated":"Hôm nay",
 "tvname":"Vĩnh Long 3"},
 {"startTime":"01:50",
 "name":"Ẩm thực nước ngoài",
 "link":"https://tv360.vn/tv?ch=219&d=2025-12-05&pid=13452405166&01:50+vinhlong3",
 "endTime":"02:10",
 "duration":1200,
 "datetime":"2025-12-05",
 "dated":"Hôm nay",
 "tvname":"Vĩnh Long 3"},
 {"startTime":"02:10",
 "name":"Phim Việt Nam: Chiếc vòng ngọc bích - Tập 44",
 "link":"https://tv360.vn/tv?ch=219&d=2025-12-05&pid=13452405169&02:10+vinhlong3",
 "endTime":"03:00",
 "duration":3000,
 "datetime":"2025-12-05",
 "dated":"Hôm nay",
 "tvname":"Vĩnh Long 3"},
 {"startTime":"03:00",
 "name":"Phim Việt Nam: Bồ công anh trước gió - Tập 4",
 "link":"https://tv360.vn/tv?ch=219&d=2025-12-05&pid=13452405172&03:00+vinhlong3",
 "endTime":"03:45",
 "duration":2700,
 "datetime":"2025-12-05",
 "dated":"Hôm nay",
 "tvname":"Vĩnh Long 3"},
 {"startTime":"03:45",
 "name":"Phim ngắn cuối tuần 2024 - Tập 78",
 "link":"https://tv360.vn/tv?ch=219&d=2025-12-05&pid=13452405175&03:45+vinhlong3",
 "endTime":"04:00",
 "duration":900,
 "datetime":"2025-12-05",
 "dated":"Hôm nay",
 "tvname":"Vĩnh Long 3"},
 {"startTime":"04:00",
 "name":"Đừng để hối tiếc - Tập 23",
 "link":"https://tv360.vn/tv?ch=219&d=2025-12-05&pid=13452405178&04:00+vinhlong3",
 "endTime":"04:15",
 "duration":900,
 "datetime":"2025-12-05",
 "dated":"Hôm nay",
 "tvname":"Vĩnh Long 3"},
 {"startTime":"04:15",
 "name":"Phim Việt Nam: Dzìa đi tía ơi - Tập 10",
 "link":"https://tv360.vn/tv?ch=219&d=2025-12-05&pid=13452405181&04:15+vinhlong3",
 "endTime":"05:00",
 "duration":2700,
 "datetime":"2025-12-05",
 "dated":"Hôm nay",
 "tvname":"Vĩnh Long 3"},
 {"startTime":"05:00",
 "name":"Giải trí truyền hình: Tình bolero 2022 - Tập 4",
 "link":"https://tv360.vn/tv?ch=219&d=2025-12-05&pid=13452405184&05:00+vinhlong3",
 "endTime":"05:45",
 "duration":2700,
 "datetime":"2025-12-05",
 "dated":"Hôm nay",
 "tvname":"Vĩnh Long 3"},
 {"startTime":"05:45",
 "name":"Phóng sự đồng hành",
 "link":"https://tv360.vn/tv?ch=219&d=2025-12-05&pid=13452405187&05:45+vinhlong3",
 "endTime":"06:00",
 "duration":900,
 "datetime":"2025-12-05",
 "dated":"Hôm nay",
 "tvname":"Vĩnh Long 3"},
 {"startTime":"06:00",
 "name":"Bí kíp hạnh phúc",
 "link":"https://tv360.vn/tv?ch=219&d=2025-12-05&pid=13452405190&06:00+vinhlong3",
 "endTime":"06:20",
 "duration":1200,
 "datetime":"2025-12-05",
 "dated":"Hôm nay",
 "tvname":"Vĩnh Long 3"},
 {"startTime":"06:20",
 "name":"Vui học! Học vui",
 "link":"https://tv360.vn/tv?ch=219&d=2025-12-05&pid=13452405193&06:20+vinhlong3",
 "endTime":"06:30",
 "duration":600,
 "datetime":"2025-12-05",
 "dated":"Hôm nay",
 "tvname":"Vĩnh Long 3"},
 {"startTime":"06:30",
 "name":"Ca nhạc",
 "link":"https://tv360.vn/tv?ch=219&d=2025-12-05&pid=13452405196&06:30+vinhlong3",
 "endTime":"07:15",
 "duration":2700,
 "datetime":"2025-12-05",
 "dated":"Hôm nay",
 "tvname":"Vĩnh Long 3"},
 {"startTime":"07:15",
 "name":"Phim Việt Nam: Sống để chuộc lỗi - Phần 2 - Tập 24",
 "link":"https://tv360.vn/tv?ch=219&d=2025-12-05&pid=13452405199&07:15+vinhlong3",
 "endTime":"08:00",
 "duration":2700,
 "datetime":"2025-12-05",
 "dated":"Hôm nay",
 "tvname":"Vĩnh Long 3"},
 {"startTime":"08:00",
 "name":"Phim Việt Nam: Một đời giông tố - Tập 9- 10",
 "link":"https://tv360.vn/tv?ch=219&d=2025-12-05&pid=13452405202&08:00+vinhlong3",
 "endTime":"09:30",
 "duration":5400,
 "datetime":"2025-12-05",
 "dated":"Hôm nay",
 "tvname":"Vĩnh Long 3"},
 {"startTime":"09:30",
 "name":"Phim sitcom: Bí mật quý ông - Tập 45",
 "link":"https://tv360.vn/tv?ch=219&d=2025-12-05&pid=13452405205&09:30+vinhlong3",
 "endTime":"10:00",
 "duration":1800,
 "datetime":"2025-12-05",
 "dated":"Hôm nay",
 "tvname":"Vĩnh Long 3"},
 {"startTime":"10:00",
 "name":"Bàn tròn hạnh phúc - Tập 31",
 "link":"https://tv360.vn/tv?ch=219&d=2025-12-05&pid=13452405208&10:00+vinhlong3",
 "endTime":"10:15",
 "duration":900,
 "datetime":"2025-12-05",
 "dated":"Hôm nay",
 "tvname":"Vĩnh Long 3"},
 {"startTime":"10:15",
 "name":"Phim Việt Nam: Ông trùm - Tập 24",
 "link":"https://tv360.vn/tv?ch=219&d=2025-12-05&pid=13452405211&10:15+vinhlong3",
 "endTime":"11:00",
 "duration":2700,
 "datetime":"2025-12-05",
 "dated":"Hôm nay",
 "tvname":"Vĩnh Long 3"},
 {"startTime":"11:00",
 "name":"Phim Việt Nam: Chiếc vòng ngọc bích - Tập 45",
 "link":"https://tv360.vn/tv?ch=219&d=2025-12-05&pid=13452405214&11:00+vinhlong3",
 "endTime":"12:00",
 "duration":3600,
 "datetime":"2025-12-05",
 "dated":"Hôm nay",
 "tvname":"Vĩnh Long 3"},
 {"startTime":"12:00",
 "name":"Phim Việt Nam: Bồ công anh trước gió - Tập 5",
 "link":"https://tv360.vn/tv?ch=219&d=2025-12-05&pid=13452405217&12:00+vinhlong3",
 "endTime":"13:00",
 "duration":3600,
 "datetime":"2025-12-05",
 "dated":"Hôm nay",
 "tvname":"Vĩnh Long 3"},
 {"startTime":"13:00",
 "name":"Phim Việt Nam: Dzìa đi tía ơi - Tập 10",
 "link":"https://tv360.vn/tv?ch=219&d=2025-12-05&pid=13452405220&13:00+vinhlong3",
 "endTime":"14:00",
 "duration":3600,
 "datetime":"2025-12-05",
 "dated":"Hôm nay",
 "tvname":"Vĩnh Long 3"},
 {"startTime":"14:00",
 "name":"Phim Việt Nam: Tía ơi đừng say - Tập 4",
 "link":"https://tv360.vn/tv?ch=219&d=2025-12-05&pid=13452405223&14:00+vinhlong3",
 "endTime":"15:00",
 "duration":3600,
 "datetime":"2025-12-05",
 "dated":"Hôm nay",
 "tvname":"Vĩnh Long 3"},
 {"startTime":"15:00",
 "name":"Phim Việt Nam: Dòng đời chảy ngược - Tập 1",
 "link":"https://tv360.vn/tv?ch=219&d=2025-12-05&pid=13452405226&15:00+vinhlong3",
 "endTime":"16:00",
 "duration":3600,
 "datetime":"2025-12-05",
 "dated":"Hôm nay",
 "tvname":"Vĩnh Long 3"},
 {"startTime":"16:00",
 "name":"Phim Việt Nam: Hoa trong bão - Tập 20",
 "link":"https://tv360.vn/tv?ch=219&d=2025-12-05&pid=13452405229&16:00+vinhlong3",
 "endTime":"17:00",
 "duration":3600,
 "datetime":"2025-12-05",
 "dated":"Hôm nay",
 "tvname":"Vĩnh Long 3"},
 {"startTime":"17:00",
 "name":"Giải trí truyền hình: Người kể chuyện tình - Tập 6",
 "link":"https://tv360.vn/tv?ch=219&d=2025-12-05&pid=13452405232&17:00+vinhlong3",
 "endTime":"18:00",
 "duration":3600,
 "datetime":"2025-12-05",
 "dated":"Hôm nay",
 "tvname":"Vĩnh Long 3"},
 {"startTime":"18:00",
 "name":"Truyền hình trực tiếp bóng đá nam Sea Games 33:   U22 Myanmar – U22 Philippines",
 "link":"https://tv360.vn/tv?ch=219&d=2025-12-05&pid=13452405235&18:00+vinhlong3",
 "endTime":"20:10",
 "duration":7800,
 "datetime":"2025-12-05",
 "dated":"Hôm nay",
 "tvname":"Vĩnh Long 3"},
 {"startTime":"20:10",
 "name":"Phim Việt Nam: Sống để chuộc lỗi - Phần 2 - Tập 25",
 "link":"https://tv360.vn/tv?ch=219&d=2025-12-05&pid=13452405238&20:10+vinhlong3",
 "endTime":"21:00",
 "duration":3000,
 "datetime":"2025-12-05",
 "dated":"Hôm nay",
 "tvname":"Vĩnh Long 3"},
 {"startTime":"21:00",
 "name":"Phim Việt Nam: Hoa trong bão - Tập 21",
 "link":"https://tv360.vn/tv?ch=219&d=2025-12-05&pid=13452405241&21:00+vinhlong3",
 "endTime":"21:45",
 "duration":2700,
 "datetime":"2025-12-05",
 "dated":"Hôm nay",
 "tvname":"Vĩnh Long 3"},
 {"startTime":"21:45",
 "name":"Phim Việt Nam: Dzìa đi tía ơi - Tập 11",
 "link":"https://tv360.vn/tv?ch=219&d=2025-12-05&pid=13452405244&21:45+vinhlong3",
 "endTime":"22:45",
 "duration":3600,
 "datetime":"2025-12-05",
 "dated":"Hôm nay",
 "tvname":"Vĩnh Long 3"},
 {"startTime":"22:45",
 "name":"Giải trí truyền hình: Tình bolero 2022 - Tập 4",
 "link":"https://tv360.vn/tv?ch=219&d=2025-12-05&pid=13452405247&22:45+vinhlong3",
 "endTime":"23:15",
 "duration":1800,
 "datetime":"2025-12-05",
 "dated":"Hôm nay",
 "tvname":"Vĩnh Long 3"},
 {"startTime":"23:15",
 "name":"Chuyến xe nhân ái",
 "link":"https://tv360.vn/tv?ch=219&d=2025-12-05&pid=13452405250&23:15+vinhlong3",
 "endTime":"23:59",
 "duration":2699,
 "datetime":"2025-12-05",
 "dated":"Hôm nay",
 "tvname":"Vĩnh Long 3"}]