[{"startTime":"00:00",
 "name":"Phim Việt Nam: Nữ luật sư – Tập 21",
 "link":"https://tv360.vn/tv?ch=26&d=2026-04-07&pid=13458854980&00:00+vinhlong2",
 "endTime":"00:30",
 "duration":1800,
 "datetime":"2026-04-07",
 "dated":"TH3",
 "tvname":"Vĩnh Long 2"},
 {"startTime":"00:30",
 "name":"Bí ẩn song sinh",
 "link":"https://tv360.vn/tv?ch=26&d=2026-04-07&pid=13458854983&00:30+vinhlong2",
 "endTime":"01:00",
 "duration":1800,
 "datetime":"2026-04-07",
 "dated":"TH3",
 "tvname":"Vĩnh Long 2"},
 {"startTime":"01:00",
 "name":"Phim Việt Nam: Giá phải trả – Tập 6",
 "link":"https://tv360.vn/tv?ch=26&d=2026-04-07&pid=13458854986&01:00+vinhlong2",
 "endTime":"01:45",
 "duration":2700,
 "datetime":"2026-04-07",
 "dated":"TH3",
 "tvname":"Vĩnh Long 2"},
 {"startTime":"01:45",
 "name":"Phim Việt Nam: Cuộc chiến nhân tâm – Tập 22",
 "link":"https://tv360.vn/tv?ch=26&d=2026-04-07&pid=13458854989&01:45+vinhlong2",
 "endTime":"02:30",
 "duration":2700,
 "datetime":"2026-04-07",
 "dated":"TH3",
 "tvname":"Vĩnh Long 2"},
 {"startTime":"02:30",
 "name":"Phim truyện Việt Nam: Người tình bố già - Tập 19",
 "link":"https://tv360.vn/tv?ch=26&d=2026-04-07&pid=13458854992&02:30+vinhlong2",
 "endTime":"03:30",
 "duration":3600,
 "datetime":"2026-04-07",
 "dated":"TH3",
 "tvname":"Vĩnh Long 2"},
 {"startTime":"03:30",
 "name":"Phim Việt Nam: Máu chảy về tim – Tập 32",
 "link":"https://tv360.vn/tv?ch=26&d=2026-04-07&pid=13458854995&03:30+vinhlong2",
 "endTime":"04:15",
 "duration":2700,
 "datetime":"2026-04-07",
 "dated":"TH3",
 "tvname":"Vĩnh Long 2"},
 {"startTime":"04:15",
 "name":"Phim ngắn cuối tuần",
 "link":"https://tv360.vn/tv?ch=26&d=2026-04-07&pid=13458854998&04:15+vinhlong2",
 "endTime":"04:30",
 "duration":900,
 "datetime":"2026-04-07",
 "dated":"TH3",
 "tvname":"Vĩnh Long 2"},
 {"startTime":"04:30",
 "name":"Thắp sáng niềm tin",
 "link":"https://tv360.vn/tv?ch=26&d=2026-04-07&pid=13458855001&04:30+vinhlong2",
 "endTime":"05:00",
 "duration":1800,
 "datetime":"2026-04-07",
 "dated":"TH3",
 "tvname":"Vĩnh Long 2"},
 {"startTime":"05:00",
 "name":"Thế giới quanh ta",
 "link":"https://tv360.vn/tv?ch=26&d=2026-04-07&pid=13458855004&05:00+vinhlong2",
 "endTime":"05:15",
 "duration":900,
 "datetime":"2026-04-07",
 "dated":"TH3",
 "tvname":"Vĩnh Long 2"},
 {"startTime":"05:15",
 "name":"Phim truyện Việt Nam: Vết thù năm tháng – Tập 7",
 "link":"https://tv360.vn/tv?ch=26&d=2026-04-07&pid=13458855007&05:15+vinhlong2",
 "endTime":"06:00",
 "duration":2700,
 "datetime":"2026-04-07",
 "dated":"TH3",
 "tvname":"Vĩnh Long 2"},
 {"startTime":"06:00",
 "name":"Chào buổi sáng",
 "link":"https://tv360.vn/tv?ch=26&d=2026-04-07&pid=13458855010&06:00+vinhlong2",
 "endTime":"06:25",
 "duration":1500,
 "datetime":"2026-04-07",
 "dated":"TH3",
 "tvname":"Vĩnh Long 2"},
 {"startTime":"06:25",
 "name":"Người đưa tin 24H",
 "link":"https://tv360.vn/tv?ch=26&d=2026-04-07&pid=13458855013&06:25+vinhlong2",
 "endTime":"07:00",
 "duration":2100,
 "datetime":"2026-04-07",
 "dated":"TH3",
 "tvname":"Vĩnh Long 2"},
 {"startTime":"07:00",
 "name":"Phim 3D-Kho tàng cổ tích Cô bé Lọ Lem – Phần 6",
 "link":"https://tv360.vn/tv?ch=26&d=2026-04-07&pid=13458855016&07:00+vinhlong2",
 "endTime":"07:15",
 "duration":900,
 "datetime":"2026-04-07",
 "dated":"TH3",
 "tvname":"Vĩnh Long 2"},
 {"startTime":"07:15",
 "name":"Giải trí truyền hình: Tỏa sáng sao đôi (Hết)",
 "link":"https://tv360.vn/tv?ch=26&d=2026-04-07&pid=13458855019&07:15+vinhlong2",
 "endTime":"08:00",
 "duration":2700,
 "datetime":"2026-04-07",
 "dated":"TH3",
 "tvname":"Vĩnh Long 2"},
 {"startTime":"08:00",
 "name":"Thế giới cổ tích: Gái khôn được chồng – Tập 35",
 "link":"https://tv360.vn/tv?ch=26&d=2026-04-07&pid=13458855022&08:00+vinhlong2",
 "endTime":"08:30",
 "duration":1800,
 "datetime":"2026-04-07",
 "dated":"TH3",
 "tvname":"Vĩnh Long 2"},
 {"startTime":"08:30",
 "name":"Nông nghiệp bền vững",
 "link":"https://tv360.vn/tv?ch=26&d=2026-04-07&pid=13458855025&08:30+vinhlong2",
 "endTime":"09:15",
 "duration":2700,
 "datetime":"2026-04-07",
 "dated":"TH3",
 "tvname":"Vĩnh Long 2"},
 {"startTime":"09:15",
 "name":"Tiếp sóng THTT: Lễ tuyên thệ nhậm chức của Chủ tịch nước",
 "link":"https://tv360.vn/tv?ch=26&d=2026-04-07&pid=13458855028&09:15+vinhlong2",
 "endTime":"10:00",
 "duration":2700,
 "datetime":"2026-04-07",
 "dated":"TH3",
 "tvname":"Vĩnh Long 2"},
 {"startTime":"10:00",
 "name":"Phim truyện Việt Nam: Vòng xoáy tình thù: Tập cuối",
 "link":"https://tv360.vn/tv?ch=26&d=2026-04-07&pid=13458855031&10:00+vinhlong2",
 "endTime":"11:00",
 "duration":3600,
 "datetime":"2026-04-07",
 "dated":"TH3",
 "tvname":"Vĩnh Long 2"},
 {"startTime":"11:00",
 "name":"Phim Việt Nam: Giá phải trả – Tập 7",
 "link":"https://tv360.vn/tv?ch=26&d=2026-04-07&pid=13458855034&11:00+vinhlong2",
 "endTime":"11:45",
 "duration":2700,
 "datetime":"2026-04-07",
 "dated":"TH3",
 "tvname":"Vĩnh Long 2"},
 {"startTime":"11:45",
 "name":"Chuyện cảnh giác",
 "link":"https://tv360.vn/tv?ch=26&d=2026-04-07&pid=13458855037&11:45+vinhlong2",
 "endTime":"12:00",
 "duration":900,
 "datetime":"2026-04-07",
 "dated":"TH3",
 "tvname":"Vĩnh Long 2"},
 {"startTime":"12:00",
 "name":"Phim truyện Việt Nam: Bình minh trên ngọn lửa – Tập 5",
 "link":"https://tv360.vn/tv?ch=26&d=2026-04-07&pid=13458855040&12:00+vinhlong2",
 "endTime":"13:00",
 "duration":3600,
 "datetime":"2026-04-07",
 "dated":"TH3",
 "tvname":"Vĩnh Long 2"},
 {"startTime":"13:00",
 "name":"Phim truyện Việt Nam: Người tình bố già - Tập 20",
 "link":"https://tv360.vn/tv?ch=26&d=2026-04-07&pid=13458855043&13:00+vinhlong2",
 "endTime":"14:00",
 "duration":3600,
 "datetime":"2026-04-07",
 "dated":"TH3",
 "tvname":"Vĩnh Long 2"},
 {"startTime":"14:00",
 "name":"Phim truyện Philippines: Vợ của chồng tôi – Tập 102",
 "link":"https://tv360.vn/tv?ch=26&d=2026-04-07&pid=13458855046&14:00+vinhlong2",
 "endTime":"14:40",
 "duration":2400,
 "datetime":"2026-04-07",
 "dated":"TH3",
 "tvname":"Vĩnh Long 2"},
 {"startTime":"14:40",
 "name":"Thế giới động vật",
 "link":"https://tv360.vn/tv?ch=26&d=2026-04-07&pid=13458855049&14:40+vinhlong2",
 "endTime":"15:00",
 "duration":1200,
 "datetime":"2026-04-07",
 "dated":"TH3",
 "tvname":"Vĩnh Long 2"},
 {"startTime":"15:00",
 "name":"Tiếp sóng THTT: Lễ tuyên thệ nhậm chức của Thủ tướng chính phủ",
 "link":"https://tv360.vn/tv?ch=26&d=2026-04-07&pid=13458855052&15:00+vinhlong2",
 "endTime":"16:30",
 "duration":5400,
 "datetime":"2026-04-07",
 "dated":"TH3",
 "tvname":"Vĩnh Long 2"},
 {"startTime":"16:30",
 "name":"Tiếp sóng THTT: Lễ tuyên thệ nhậm chức của Chánh án Tòa án nhân dân tối cao",
 "link":"https://tv360.vn/tv?ch=26&d=2026-04-07&pid=13458874510&16:30+vinhlong2",
 "endTime":"17:00",
 "duration":1800,
 "datetime":"2026-04-07",
 "dated":"TH3",
 "tvname":"Vĩnh Long 2"},
 {"startTime":"17:00",
 "name":"Phim truyện Việt Nam: Trái tim bất hạnh – Tập 2",
 "link":"https://tv360.vn/tv?ch=26&d=2026-04-07&pid=13458874513&17:00+vinhlong2",
 "endTime":"17:50",
 "duration":3000,
 "datetime":"2026-04-07",
 "dated":"TH3",
 "tvname":"Vĩnh Long 2"},
 {"startTime":"17:50",
 "name":"Đừng để hối tiếc",
 "link":"https://tv360.vn/tv?ch=26&d=2026-04-07&pid=13458874516&17:50+vinhlong2",
 "endTime":"18:00",
 "duration":600,
 "datetime":"2026-04-07",
 "dated":"TH3",
 "tvname":"Vĩnh Long 2"},
 {"startTime":"18:00",
 "name":"Phim truyện Thái Lan: Cô dâu của Thần Rắn – Tập 23",
 "link":"https://tv360.vn/tv?ch=26&d=2026-04-07&pid=13458874519&18:00+vinhlong2",
 "endTime":"19:00",
 "duration":3600,
 "datetime":"2026-04-07",
 "dated":"TH3",
 "tvname":"Vĩnh Long 2"},
 {"startTime":"19:00",
 "name":"Tiếp chuyển Thời sự THVN",
 "link":"https://tv360.vn/tv?ch=26&d=2026-04-07&pid=13458874522&19:00+vinhlong2",
 "endTime":"19:40",
 "duration":2400,
 "datetime":"2026-04-07",
 "dated":"TH3",
 "tvname":"Vĩnh Long 2"},
 {"startTime":"19:40",
 "name":"Nông thôn ngày nay",
 "link":"https://tv360.vn/tv?ch=26&d=2026-04-07&pid=13458874525&19:40+vinhlong2",
 "endTime":"20:00",
 "duration":1200,
 "datetime":"2026-04-07",
 "dated":"TH3",
 "tvname":"Vĩnh Long 2"},
 {"startTime":"20:00",
 "name":"Giải trí truyền hình: Lò võ tiếu lâm",
 "link":"https://tv360.vn/tv?ch=26&d=2026-04-07&pid=13458874528&20:00+vinhlong2",
 "endTime":"21:00",
 "duration":3600,
 "datetime":"2026-04-07",
 "dated":"TH3",
 "tvname":"Vĩnh Long 2"},
 {"startTime":"21:00",
 "name":"Phim truyện Việt Nam: Má ơi tỉnh mộng - Tập 11",
 "link":"https://tv360.vn/tv?ch=26&d=2026-04-07&pid=13458874531&21:00+vinhlong2",
 "endTime":"21:45",
 "duration":2700,
 "datetime":"2026-04-07",
 "dated":"TH3",
 "tvname":"Vĩnh Long 2"},
 {"startTime":"21:45",
 "name":"Đời sống pháp luật",
 "link":"https://tv360.vn/tv?ch=26&d=2026-04-07&pid=13458874534&21:45+vinhlong2",
 "endTime":"22:00",
 "duration":900,
 "datetime":"2026-04-07",
 "dated":"TH3",
 "tvname":"Vĩnh Long 2"},
 {"startTime":"22:00",
 "name":"Thế giới 24H",
 "link":"https://tv360.vn/tv?ch=26&d=2026-04-07&pid=13458874537&22:00+vinhlong2",
 "endTime":"22:15",
 "duration":900,
 "datetime":"2026-04-07",
 "dated":"TH3",
 "tvname":"Vĩnh Long 2"},
 {"startTime":"22:15",
 "name":"Thế giới cổ tích: Gái khôn được chồng – Tập 35",
 "link":"https://tv360.vn/tv?ch=26&d=2026-04-07&pid=13458874540&22:15+vinhlong2",
 "endTime":"22:45",
 "duration":1800,
 "datetime":"2026-04-07",
 "dated":"TH3",
 "tvname":"Vĩnh Long 2"},
 {"startTime":"22:45",
 "name":"Gia đình khó dễ",
 "link":"https://tv360.vn/tv?ch=26&d=2026-04-07&pid=13458874543&22:45+vinhlong2",
 "endTime":"23:00",
 "duration":900,
 "datetime":"2026-04-07",
 "dated":"TH3",
 "tvname":"Vĩnh Long 2"},
 {"startTime":"23:00",
 "name":"Phim Việt Nam: Vết thù năm tháng – Tập 7",
 "link":"https://tv360.vn/tv?ch=26&d=2026-04-07&pid=13458874546&23:00+vinhlong2",
 "endTime":"23:45",
 "duration":2700,
 "datetime":"2026-04-07",
 "dated":"TH3",
 "tvname":"Vĩnh Long 2"},
 {"startTime":"23:45",
 "name":"Phim Việt Nam: Nữ luật sư – Tập 22",
 "link":"https://tv360.vn/tv?ch=26&d=2026-04-07&pid=13458874549&23:45+vinhlong2",
 "endTime":"23:59",
 "duration":899,
 "datetime":"2026-04-07",
 "dated":"TH3",
 "tvname":"Vĩnh Long 2"}]